[
  {
    "slug": "inspect",
    "shard": "python/shards/inspect/i.json"
  },
  {
    "slug": "inspect/BufferFlags/ANY_CONTIGUOUS",
    "shard": "python/shards/inspect/a.json"
  },
  {
    "slug": "inspect/BufferFlags/CONTIG",
    "shard": "python/shards/inspect/c.json"
  },
  {
    "slug": "inspect/BufferFlags/CONTIG_RO",
    "shard": "python/shards/inspect/c.json"
  },
  {
    "slug": "inspect/BufferFlags/C_CONTIGUOUS",
    "shard": "python/shards/inspect/c.json"
  },
  {
    "slug": "inspect/BufferFlags/FORMAT",
    "shard": "python/shards/inspect/f.json"
  },
  {
    "slug": "inspect/BufferFlags/FULL",
    "shard": "python/shards/inspect/f.json"
  },
  {
    "slug": "inspect/BufferFlags/FULL_RO",
    "shard": "python/shards/inspect/f.json"
  },
  {
    "slug": "inspect/BufferFlags/F_CONTIGUOUS",
    "shard": "python/shards/inspect/f.json"
  },
  {
    "slug": "inspect/BufferFlags/INDIRECT",
    "shard": "python/shards/inspect/i.json"
  },
  {
    "slug": "inspect/BufferFlags/ND",
    "shard": "python/shards/inspect/n.json"
  },
  {
    "slug": "inspect/BufferFlags/READ",
    "shard": "python/shards/inspect/r.json"
  },
  {
    "slug": "inspect/BufferFlags/RECORDS",
    "shard": "python/shards/inspect/r.json"
  },
  {
    "slug": "inspect/BufferFlags/RECORDS_RO",
    "shard": "python/shards/inspect/r.json"
  },
  {
    "slug": "inspect/BufferFlags/SIMPLE",
    "shard": "python/shards/inspect/s.json"
  },
  {
    "slug": "inspect/BufferFlags/STRIDED",
    "shard": "python/shards/inspect/s.json"
  },
  {
    "slug": "inspect/BufferFlags/STRIDED_RO",
    "shard": "python/shards/inspect/s.json"
  },
  {
    "slug": "inspect/BufferFlags/STRIDES",
    "shard": "python/shards/inspect/s.json"
  },
  {
    "slug": "inspect/BufferFlags/WRITABLE",
    "shard": "python/shards/inspect/w.json"
  },
  {
    "slug": "inspect/BufferFlags/WRITE",
    "shard": "python/shards/inspect/w.json"
  },
  {
    "slug": "inspect/Parameter/annotation",
    "shard": "python/shards/inspect/a.json"
  },
  {
    "slug": "inspect/BoundArguments/args",
    "shard": "python/shards/inspect/a.json"
  },
  {
    "slug": "inspect/BoundArguments/arguments",
    "shard": "python/shards/inspect/a.json"
  },
  {
    "slug": "inspect/FrameInfo/code_context",
    "shard": "python/shards/inspect/c.json"
  },
  {
    "slug": "inspect/Traceback/code_context",
    "shard": "python/shards/inspect/c.json"
  },
  {
    "slug": "inspect/Parameter/default",
    "shard": "python/shards/inspect/d.json"
  },
  {
    "slug": "inspect/kind/description",
    "shard": "python/shards/inspect/d.json"
  },
  {
    "slug": "inspect/Signature/empty",
    "shard": "python/shards/inspect/e.json"
  },
  {
    "slug": "inspect/Parameter/empty",
    "shard": "python/shards/inspect/e.json"
  },
  {
    "slug": "inspect/FrameInfo/filename",
    "shard": "python/shards/inspect/f.json"
  },
  {
    "slug": "inspect/Traceback/filename",
    "shard": "python/shards/inspect/f.json"
  },
  {
    "slug": "inspect/FrameInfo/frame",
    "shard": "python/shards/inspect/f.json"
  },
  {
    "slug": "inspect/FrameInfo/function",
    "shard": "python/shards/inspect/f.json"
  },
  {
    "slug": "inspect/Traceback/function",
    "shard": "python/shards/inspect/f.json"
  },
  {
    "slug": "inspect/FrameInfo/index",
    "shard": "python/shards/inspect/i.json"
  },
  {
    "slug": "inspect/Traceback/index",
    "shard": "python/shards/inspect/i.json"
  },
  {
    "slug": "inspect/Parameter/kind",
    "shard": "python/shards/inspect/k.json"
  },
  {
    "slug": "inspect/BoundArguments/kwargs",
    "shard": "python/shards/inspect/k.json"
  },
  {
    "slug": "inspect/FrameInfo/lineno",
    "shard": "python/shards/inspect/l.json"
  },
  {
    "slug": "inspect/Traceback/lineno",
    "shard": "python/shards/inspect/l.json"
  },
  {
    "slug": "inspect/Parameter/name",
    "shard": "python/shards/inspect/n.json"
  },
  {
    "slug": "inspect/Signature/parameters",
    "shard": "python/shards/inspect/p.json"
  },
  {
    "slug": "inspect/FrameInfo/positions",
    "shard": "python/shards/inspect/p.json"
  },
  {
    "slug": "inspect/Traceback/positions",
    "shard": "python/shards/inspect/p.json"
  },
  {
    "slug": "inspect/Signature/return_annotation",
    "shard": "python/shards/inspect/r.json"
  },
  {
    "slug": "inspect/BoundArguments/signature",
    "shard": "python/shards/inspect/s.json"
  },
  {
    "slug": "inspect/BoundArguments",
    "shard": "python/shards/inspect/b.json"
  },
  {
    "slug": "inspect/BufferFlags",
    "shard": "python/shards/inspect/b.json"
  },
  {
    "slug": "inspect/FrameInfo",
    "shard": "python/shards/inspect/f.json"
  },
  {
    "slug": "inspect/Parameter",
    "shard": "python/shards/inspect/p.json"
  },
  {
    "slug": "inspect/Signature",
    "shard": "python/shards/inspect/s.json"
  },
  {
    "slug": "inspect/Traceback",
    "shard": "python/shards/inspect/t.json"
  },
  {
    "slug": "inspect/CO_ASYNC_GENERATOR",
    "shard": "python/shards/inspect/c.json"
  },
  {
    "slug": "inspect/CO_COROUTINE",
    "shard": "python/shards/inspect/c.json"
  },
  {
    "slug": "inspect/CO_GENERATOR",
    "shard": "python/shards/inspect/c.json"
  },
  {
    "slug": "inspect/CO_HAS_DOCSTRING",
    "shard": "python/shards/inspect/c.json"
  },
  {
    "slug": "inspect/CO_ITERABLE_COROUTINE",
    "shard": "python/shards/inspect/c.json"
  },
  {
    "slug": "inspect/CO_METHOD",
    "shard": "python/shards/inspect/c.json"
  },
  {
    "slug": "inspect/CO_NESTED",
    "shard": "python/shards/inspect/c.json"
  },
  {
    "slug": "inspect/CO_NEWLOCALS",
    "shard": "python/shards/inspect/c.json"
  },
  {
    "slug": "inspect/CO_OPTIMIZED",
    "shard": "python/shards/inspect/c.json"
  },
  {
    "slug": "inspect/CO_VARARGS",
    "shard": "python/shards/inspect/c.json"
  },
  {
    "slug": "inspect/CO_VARKEYWORDS",
    "shard": "python/shards/inspect/c.json"
  },
  {
    "slug": "inspect/cleandoc",
    "shard": "python/shards/inspect/c.json"
  },
  {
    "slug": "inspect/currentframe",
    "shard": "python/shards/inspect/c.json"
  },
  {
    "slug": "inspect/formatargvalues",
    "shard": "python/shards/inspect/f.json"
  },
  {
    "slug": "inspect/get_annotations",
    "shard": "python/shards/inspect/g.json"
  },
  {
    "slug": "inspect/getargvalues",
    "shard": "python/shards/inspect/g.json"
  },
  {
    "slug": "inspect/getasyncgenlocals",
    "shard": "python/shards/inspect/g.json"
  },
  {
    "slug": "inspect/getasyncgenstate",
    "shard": "python/shards/inspect/g.json"
  },
  {
    "slug": "inspect/getattr_static",
    "shard": "python/shards/inspect/g.json"
  },
  {
    "slug": "inspect/getcallargs",
    "shard": "python/shards/inspect/g.json"
  },
  {
    "slug": "inspect/getclasstree",
    "shard": "python/shards/inspect/g.json"
  },
  {
    "slug": "inspect/getclosurevars",
    "shard": "python/shards/inspect/g.json"
  },
  {
    "slug": "inspect/getcomments",
    "shard": "python/shards/inspect/g.json"
  },
  {
    "slug": "inspect/getcoroutinelocals",
    "shard": "python/shards/inspect/g.json"
  },
  {
    "slug": "inspect/getcoroutinestate",
    "shard": "python/shards/inspect/g.json"
  },
  {
    "slug": "inspect/getdoc",
    "shard": "python/shards/inspect/g.json"
  },
  {
    "slug": "inspect/getfile",
    "shard": "python/shards/inspect/g.json"
  },
  {
    "slug": "inspect/getframeinfo",
    "shard": "python/shards/inspect/g.json"
  },
  {
    "slug": "inspect/getfullargspec",
    "shard": "python/shards/inspect/g.json"
  },
  {
    "slug": "inspect/getgeneratorlocals",
    "shard": "python/shards/inspect/g.json"
  },
  {
    "slug": "inspect/getgeneratorstate",
    "shard": "python/shards/inspect/g.json"
  },
  {
    "slug": "inspect/getinnerframes",
    "shard": "python/shards/inspect/g.json"
  },
  {
    "slug": "inspect/getmembers",
    "shard": "python/shards/inspect/g.json"
  },
  {
    "slug": "inspect/getmembers_static",
    "shard": "python/shards/inspect/g.json"
  },
  {
    "slug": "inspect/getmodule",
    "shard": "python/shards/inspect/g.json"
  },
  {
    "slug": "inspect/getmodulename",
    "shard": "python/shards/inspect/g.json"
  },
  {
    "slug": "inspect/getmro",
    "shard": "python/shards/inspect/g.json"
  },
  {
    "slug": "inspect/getouterframes",
    "shard": "python/shards/inspect/g.json"
  },
  {
    "slug": "inspect/getsource",
    "shard": "python/shards/inspect/g.json"
  },
  {
    "slug": "inspect/getsourcefile",
    "shard": "python/shards/inspect/g.json"
  },
  {
    "slug": "inspect/getsourcelines",
    "shard": "python/shards/inspect/g.json"
  },
  {
    "slug": "inspect/isabstract",
    "shard": "python/shards/inspect/i.json"
  },
  {
    "slug": "inspect/isasyncgen",
    "shard": "python/shards/inspect/i.json"
  },
  {
    "slug": "inspect/isasyncgenfunction",
    "shard": "python/shards/inspect/i.json"
  },
  {
    "slug": "inspect/isawaitable",
    "shard": "python/shards/inspect/i.json"
  },
  {
    "slug": "inspect/isbuiltin",
    "shard": "python/shards/inspect/i.json"
  },
  {
    "slug": "inspect/isclass",
    "shard": "python/shards/inspect/i.json"
  },
  {
    "slug": "inspect/iscode",
    "shard": "python/shards/inspect/i.json"
  },
  {
    "slug": "inspect/iscoroutine",
    "shard": "python/shards/inspect/i.json"
  },
  {
    "slug": "inspect/iscoroutinefunction",
    "shard": "python/shards/inspect/i.json"
  },
  {
    "slug": "inspect/isdatadescriptor",
    "shard": "python/shards/inspect/i.json"
  },
  {
    "slug": "inspect/isframe",
    "shard": "python/shards/inspect/i.json"
  },
  {
    "slug": "inspect/isfunction",
    "shard": "python/shards/inspect/i.json"
  },
  {
    "slug": "inspect/isgenerator",
    "shard": "python/shards/inspect/i.json"
  },
  {
    "slug": "inspect/isgeneratorfunction",
    "shard": "python/shards/inspect/i.json"
  },
  {
    "slug": "inspect/isgetsetdescriptor",
    "shard": "python/shards/inspect/i.json"
  },
  {
    "slug": "inspect/ismemberdescriptor",
    "shard": "python/shards/inspect/i.json"
  },
  {
    "slug": "inspect/ismethod",
    "shard": "python/shards/inspect/i.json"
  },
  {
    "slug": "inspect/ismethoddescriptor",
    "shard": "python/shards/inspect/i.json"
  },
  {
    "slug": "inspect/ismethodwrapper",
    "shard": "python/shards/inspect/i.json"
  },
  {
    "slug": "inspect/ismodule",
    "shard": "python/shards/inspect/i.json"
  },
  {
    "slug": "inspect/ispackage",
    "shard": "python/shards/inspect/i.json"
  },
  {
    "slug": "inspect/isroutine",
    "shard": "python/shards/inspect/i.json"
  },
  {
    "slug": "inspect/istraceback",
    "shard": "python/shards/inspect/i.json"
  },
  {
    "slug": "inspect/markcoroutinefunction",
    "shard": "python/shards/inspect/m.json"
  },
  {
    "slug": "inspect/signature",
    "shard": "python/shards/inspect/s.json"
  },
  {
    "slug": "inspect/stack",
    "shard": "python/shards/inspect/s.json"
  },
  {
    "slug": "inspect/trace",
    "shard": "python/shards/inspect/t.json"
  },
  {
    "slug": "inspect/unwrap",
    "shard": "python/shards/inspect/u.json"
  },
  {
    "slug": "inspect/BoundArguments/apply_defaults",
    "shard": "python/shards/inspect/a.json"
  },
  {
    "slug": "inspect/Signature/bind",
    "shard": "python/shards/inspect/b.json"
  },
  {
    "slug": "inspect/Signature/bind_partial",
    "shard": "python/shards/inspect/b.json"
  },
  {
    "slug": "inspect/Signature/format",
    "shard": "python/shards/inspect/f.json"
  },
  {
    "slug": "inspect/Signature/from_callable",
    "shard": "python/shards/inspect/f.json"
  },
  {
    "slug": "inspect/Signature/replace",
    "shard": "python/shards/inspect/r.json"
  },
  {
    "slug": "inspect/Parameter/replace",
    "shard": "python/shards/inspect/r.json"
  }
]