[
  {
    "slug": "unittest.mock",
    "shard": "python/shards/unittest.mock/u.json"
  },
  {
    "slug": "unittest.mock/ThreadingMock/DEFAULT_TIMEOUT",
    "shard": "python/shards/unittest.mock/d.json"
  },
  {
    "slug": "unittest.mock/Mock/__class__",
    "shard": "python/shards/unittest.mock/_.json"
  },
  {
    "slug": "unittest.mock/AsyncMock/await_args",
    "shard": "python/shards/unittest.mock/a.json"
  },
  {
    "slug": "unittest.mock/AsyncMock/await_args_list",
    "shard": "python/shards/unittest.mock/a.json"
  },
  {
    "slug": "unittest.mock/AsyncMock/await_count",
    "shard": "python/shards/unittest.mock/a.json"
  },
  {
    "slug": "unittest.mock/Mock/call_args",
    "shard": "python/shards/unittest.mock/c.json"
  },
  {
    "slug": "unittest.mock/Mock/call_args_list",
    "shard": "python/shards/unittest.mock/c.json"
  },
  {
    "slug": "unittest.mock/Mock/call_count",
    "shard": "python/shards/unittest.mock/c.json"
  },
  {
    "slug": "unittest.mock/Mock/called",
    "shard": "python/shards/unittest.mock/c.json"
  },
  {
    "slug": "unittest.mock/Mock/method_calls",
    "shard": "python/shards/unittest.mock/m.json"
  },
  {
    "slug": "unittest.mock/Mock/mock_calls",
    "shard": "python/shards/unittest.mock/m.json"
  },
  {
    "slug": "unittest.mock/Mock/return_value",
    "shard": "python/shards/unittest.mock/r.json"
  },
  {
    "slug": "unittest.mock/Mock/side_effect",
    "shard": "python/shards/unittest.mock/s.json"
  },
  {
    "slug": "unittest.mock/AsyncMock",
    "shard": "python/shards/unittest.mock/a.json"
  },
  {
    "slug": "unittest.mock/MagicMock",
    "shard": "python/shards/unittest.mock/m.json"
  },
  {
    "slug": "unittest.mock/Mock",
    "shard": "python/shards/unittest.mock/m.json"
  },
  {
    "slug": "unittest.mock/NonCallableMagicMock",
    "shard": "python/shards/unittest.mock/n.json"
  },
  {
    "slug": "unittest.mock/NonCallableMock",
    "shard": "python/shards/unittest.mock/n.json"
  },
  {
    "slug": "unittest.mock/PropertyMock",
    "shard": "python/shards/unittest.mock/p.json"
  },
  {
    "slug": "unittest.mock/ThreadingMock",
    "shard": "python/shards/unittest.mock/t.json"
  },
  {
    "slug": "unittest.mock/mock/ANY",
    "shard": "python/shards/unittest.mock/a.json"
  },
  {
    "slug": "unittest.mock/mock/DEFAULT",
    "shard": "python/shards/unittest.mock/d.json"
  },
  {
    "slug": "unittest.mock/mock/FILTER_DIR",
    "shard": "python/shards/unittest.mock/f.json"
  },
  {
    "slug": "unittest.mock/mock/sentinel",
    "shard": "python/shards/unittest.mock/s.json"
  },
  {
    "slug": "unittest.mock/call",
    "shard": "python/shards/unittest.mock/c.json"
  },
  {
    "slug": "unittest.mock/create_autospec",
    "shard": "python/shards/unittest.mock/c.json"
  },
  {
    "slug": "unittest.mock/dict",
    "shard": "python/shards/unittest.mock/d.json"
  },
  {
    "slug": "unittest.mock/mock_open",
    "shard": "python/shards/unittest.mock/m.json"
  },
  {
    "slug": "unittest.mock/multiple",
    "shard": "python/shards/unittest.mock/m.json"
  },
  {
    "slug": "unittest.mock/object",
    "shard": "python/shards/unittest.mock/o.json"
  },
  {
    "slug": "unittest.mock/patch",
    "shard": "python/shards/unittest.mock/p.json"
  },
  {
    "slug": "unittest.mock/seal",
    "shard": "python/shards/unittest.mock/s.json"
  },
  {
    "slug": "unittest.mock/stopall",
    "shard": "python/shards/unittest.mock/s.json"
  },
  {
    "slug": "unittest.mock/Mock/__dir__",
    "shard": "python/shards/unittest.mock/_.json"
  },
  {
    "slug": "unittest.mock/Mock/_get_child_mock",
    "shard": "python/shards/unittest.mock/_.json"
  },
  {
    "slug": "unittest.mock/AsyncMock/assert_any_await",
    "shard": "python/shards/unittest.mock/a.json"
  },
  {
    "slug": "unittest.mock/Mock/assert_any_call",
    "shard": "python/shards/unittest.mock/a.json"
  },
  {
    "slug": "unittest.mock/AsyncMock/assert_awaited",
    "shard": "python/shards/unittest.mock/a.json"
  },
  {
    "slug": "unittest.mock/AsyncMock/assert_awaited_once",
    "shard": "python/shards/unittest.mock/a.json"
  },
  {
    "slug": "unittest.mock/AsyncMock/assert_awaited_once_with",
    "shard": "python/shards/unittest.mock/a.json"
  },
  {
    "slug": "unittest.mock/AsyncMock/assert_awaited_with",
    "shard": "python/shards/unittest.mock/a.json"
  },
  {
    "slug": "unittest.mock/Mock/assert_called",
    "shard": "python/shards/unittest.mock/a.json"
  },
  {
    "slug": "unittest.mock/Mock/assert_called_once",
    "shard": "python/shards/unittest.mock/a.json"
  },
  {
    "slug": "unittest.mock/Mock/assert_called_once_with",
    "shard": "python/shards/unittest.mock/a.json"
  },
  {
    "slug": "unittest.mock/Mock/assert_called_with",
    "shard": "python/shards/unittest.mock/a.json"
  },
  {
    "slug": "unittest.mock/AsyncMock/assert_has_awaits",
    "shard": "python/shards/unittest.mock/a.json"
  },
  {
    "slug": "unittest.mock/Mock/assert_has_calls",
    "shard": "python/shards/unittest.mock/a.json"
  },
  {
    "slug": "unittest.mock/AsyncMock/assert_not_awaited",
    "shard": "python/shards/unittest.mock/a.json"
  },
  {
    "slug": "unittest.mock/Mock/assert_not_called",
    "shard": "python/shards/unittest.mock/a.json"
  },
  {
    "slug": "unittest.mock/Mock/attach_mock",
    "shard": "python/shards/unittest.mock/a.json"
  },
  {
    "slug": "unittest.mock/call/call_list",
    "shard": "python/shards/unittest.mock/c.json"
  },
  {
    "slug": "unittest.mock/Mock/configure_mock",
    "shard": "python/shards/unittest.mock/c.json"
  },
  {
    "slug": "unittest.mock/Mock/mock_add_spec",
    "shard": "python/shards/unittest.mock/m.json"
  },
  {
    "slug": "unittest.mock/Mock/reset_mock",
    "shard": "python/shards/unittest.mock/r.json"
  },
  {
    "slug": "unittest.mock/AsyncMock/reset_mock",
    "shard": "python/shards/unittest.mock/r.json"
  },
  {
    "slug": "unittest.mock/ThreadingMock/wait_until_any_call_with",
    "shard": "python/shards/unittest.mock/w.json"
  },
  {
    "slug": "unittest.mock/ThreadingMock/wait_until_called",
    "shard": "python/shards/unittest.mock/w.json"
  }
]