{
  "java.util.concurrent.atomic/AtomicBoolean/weakCompareAndSet": {
    "id": "java.util.concurrent.atomic.AtomicBoolean.weakCompareAndSet",
    "name": "weakCompareAndSet",
    "type": "method",
    "parent": "AtomicBoolean",
    "signatures": [
      "public boolean weakCompareAndSet(boolean expectedValue, boolean newValue)"
    ],
    "signature_hash": "d6b806b3eb6c37a065c8874ba8446f26c1cbeae3ecbcaa31978e3e7b85521bb1",
    "url": "https://docs.oracle.com/en/java/javase/25/docs/api/java.base/java/util/concurrent/atomic/AtomicBoolean.html",
    "parameters": [
      {
        "name": "expectedValue",
        "type": "boolean",
        "has_default": false,
        "default_value": null,
        "is_keyword_only": false,
        "is_var_args": false,
        "is_var_kwargs": false,
        "description": ""
      },
      {
        "name": "newValue",
        "type": "boolean",
        "has_default": false,
        "default_value": null,
        "is_keyword_only": false,
        "is_var_args": false,
        "is_var_kwargs": false,
        "description": ""
      }
    ],
    "return_type": "boolean",
    "exceptions": [],
    "description": "Deprecated.This method has plain memory effects but the method\nname implies volatile memory effects (see methods such ascompareAndExchange(boolean, boolean)andcompareAndSet(boolean, boolean)).",
    "example": "",
    "articles": [],
    "info": {
      "status": "empty",
      "excerpt": "Deprecated.This method has plain memory effects but the method\nname implies volatile memory effects (see methods such ascompareAndExchange(boolean, boolean)andcompareAndSet(boolean, boolean)).",
      "keyword": "",
      "seo_position": 0,
      "visits": 0
    },
    "createdDate": "2026-03-11T23:15:40.855466",
    "updatedDate": "2026-03-11T23:15:40.855467",
    "metadata": {
      "deprecated": true,
      "deprecated_version": "unknown",
      "added_version": "1.5",
      "tags": [],
      "difficulty": null,
      "popularity_score": 0
    }
  },
  "java.util.concurrent.atomic/AtomicInteger/weakCompareAndSet": {
    "id": "java.util.concurrent.atomic.AtomicInteger.weakCompareAndSet",
    "name": "weakCompareAndSet",
    "type": "method",
    "parent": "AtomicInteger",
    "signatures": [
      "public final boolean weakCompareAndSet(int expectedValue, int newValue)"
    ],
    "signature_hash": "87f89f16a3c7b9b105c44e4249ef15eca6b91e0b970459e442743a712c444b97",
    "url": "https://docs.oracle.com/en/java/javase/25/docs/api/java.base/java/util/concurrent/atomic/AtomicInteger.html",
    "parameters": [
      {
        "name": "expectedValue",
        "type": "int",
        "has_default": false,
        "default_value": null,
        "is_keyword_only": false,
        "is_var_args": false,
        "is_var_kwargs": false,
        "description": ""
      },
      {
        "name": "newValue",
        "type": "int",
        "has_default": false,
        "default_value": null,
        "is_keyword_only": false,
        "is_var_args": false,
        "is_var_kwargs": false,
        "description": ""
      }
    ],
    "return_type": "final boolean",
    "exceptions": [],
    "description": "Deprecated.This method has plain memory effects but the method\nname implies volatile memory effects (see methods such ascompareAndExchange(int, int)andcompareAndSet(int, int)).",
    "example": "",
    "articles": [],
    "info": {
      "status": "empty",
      "excerpt": "Deprecated.This method has plain memory effects but the method\nname implies volatile memory effects (see methods such ascompareAndExchange(int, int)andcompareAndSet(int, int)).",
      "keyword": "",
      "seo_position": 0,
      "visits": 0
    },
    "createdDate": "2026-03-11T23:15:40.856627",
    "updatedDate": "2026-03-11T23:15:40.856629",
    "metadata": {
      "deprecated": true,
      "deprecated_version": "unknown",
      "added_version": "1.5",
      "tags": [],
      "difficulty": null,
      "popularity_score": 0
    }
  },
  "java.util.concurrent.atomic/AtomicLong/weakCompareAndSet": {
    "id": "java.util.concurrent.atomic.AtomicLong.weakCompareAndSet",
    "name": "weakCompareAndSet",
    "type": "method",
    "parent": "AtomicLong",
    "signatures": [
      "public final boolean weakCompareAndSet(long expectedValue, long newValue)"
    ],
    "signature_hash": "39c511fb15b10fb461be26b923062eda1487ebf66598786506dcccbab5c470f6",
    "url": "https://docs.oracle.com/en/java/javase/25/docs/api/java.base/java/util/concurrent/atomic/AtomicLong.html",
    "parameters": [
      {
        "name": "expectedValue",
        "type": "long",
        "has_default": false,
        "default_value": null,
        "is_keyword_only": false,
        "is_var_args": false,
        "is_var_kwargs": false,
        "description": ""
      },
      {
        "name": "newValue",
        "type": "long",
        "has_default": false,
        "default_value": null,
        "is_keyword_only": false,
        "is_var_args": false,
        "is_var_kwargs": false,
        "description": ""
      }
    ],
    "return_type": "final boolean",
    "exceptions": [],
    "description": "Deprecated.This method has plain memory effects but the method\nname implies volatile memory effects (see methods such ascompareAndExchange(long, long)andcompareAndSet(long, long)).",
    "example": "",
    "articles": [],
    "info": {
      "status": "empty",
      "excerpt": "Deprecated.This method has plain memory effects but the method\nname implies volatile memory effects (see methods such ascompareAndExchange(long, long)andcompareAndSet(long, long)).",
      "keyword": "",
      "seo_position": 0,
      "visits": 0
    },
    "createdDate": "2026-03-11T23:15:40.857538",
    "updatedDate": "2026-03-11T23:15:40.857540",
    "metadata": {
      "deprecated": true,
      "deprecated_version": "unknown",
      "added_version": "1.5",
      "tags": [],
      "difficulty": null,
      "popularity_score": 0
    }
  },
  "java.util.concurrent.atomic/AtomicReference/weakCompareAndSet": {
    "id": "java.util.concurrent.atomic.AtomicReference.weakCompareAndSet",
    "name": "weakCompareAndSet",
    "type": "method",
    "parent": "AtomicReference",
    "signatures": [
      "public final boolean weakCompareAndSet(V expectedValue, V newValue)"
    ],
    "signature_hash": "45b037254e57c93eb1b29a9811eea40cb86569a2f4c927df078ef45d4dc14ba6",
    "url": "https://docs.oracle.com/en/java/javase/25/docs/api/java.base/java/util/concurrent/atomic/AtomicReference.html",
    "parameters": [
      {
        "name": "expectedValue",
        "type": "V",
        "has_default": false,
        "default_value": null,
        "is_keyword_only": false,
        "is_var_args": false,
        "is_var_kwargs": false,
        "description": ""
      },
      {
        "name": "newValue",
        "type": "V",
        "has_default": false,
        "default_value": null,
        "is_keyword_only": false,
        "is_var_args": false,
        "is_var_kwargs": false,
        "description": ""
      }
    ],
    "return_type": "final boolean",
    "exceptions": [],
    "description": "Deprecated.This method has plain memory effects but the method\nname implies volatile memory effects (see methods such ascompareAndExchange(V, V)andcompareAndSet(V, V)).",
    "example": "",
    "articles": [],
    "info": {
      "status": "empty",
      "excerpt": "Deprecated.This method has plain memory effects but the method\nname implies volatile memory effects (see methods such ascompareAndExchange(V, V)andcompareAndSet(V, V)).",
      "keyword": "",
      "seo_position": 0,
      "visits": 0
    },
    "createdDate": "2026-03-11T23:15:40.858180",
    "updatedDate": "2026-03-11T23:15:40.858181",
    "metadata": {
      "deprecated": true,
      "deprecated_version": "unknown",
      "added_version": "1.5",
      "tags": [],
      "difficulty": null,
      "popularity_score": 0
    }
  },
  "java.util.concurrent.atomic/AtomicIntegerArray/weakCompareAndSet": {
    "id": "java.util.concurrent.atomic.AtomicIntegerArray.weakCompareAndSet",
    "name": "weakCompareAndSet",
    "type": "method",
    "parent": "AtomicIntegerArray",
    "signatures": [
      "public final boolean weakCompareAndSet(int i, int expectedValue, int newValue)"
    ],
    "signature_hash": "ba918919414b081556b94548e04cdc1924a8399ba4558a3a60e8ac9c7d394627",
    "url": "https://docs.oracle.com/en/java/javase/25/docs/api/java.base/java/util/concurrent/atomic/AtomicIntegerArray.html",
    "parameters": [
      {
        "name": "i",
        "type": "int",
        "has_default": false,
        "default_value": null,
        "is_keyword_only": false,
        "is_var_args": false,
        "is_var_kwargs": false,
        "description": ""
      },
      {
        "name": "expectedValue",
        "type": "int",
        "has_default": false,
        "default_value": null,
        "is_keyword_only": false,
        "is_var_args": false,
        "is_var_kwargs": false,
        "description": ""
      },
      {
        "name": "newValue",
        "type": "int",
        "has_default": false,
        "default_value": null,
        "is_keyword_only": false,
        "is_var_args": false,
        "is_var_kwargs": false,
        "description": ""
      }
    ],
    "return_type": "final boolean",
    "exceptions": [],
    "description": "Deprecated.This method has plain memory effects but the method\nname implies volatile memory effects (see methods such ascompareAndExchange(int, int, int)andcompareAndSet(int, int, int)).",
    "example": "",
    "articles": [],
    "info": {
      "status": "empty",
      "excerpt": "Deprecated.This method has plain memory effects but the method\nname implies volatile memory effects (see methods such ascompareAndExchange(int, int, int)andcompareAndSet(int, int, int)).",
      "keyword": "",
      "seo_position": 0,
      "visits": 0
    },
    "createdDate": "2026-03-11T23:15:40.859059",
    "updatedDate": "2026-03-11T23:15:40.859060",
    "metadata": {
      "deprecated": true,
      "deprecated_version": "unknown",
      "added_version": "1.5",
      "tags": [],
      "difficulty": null,
      "popularity_score": 0
    }
  },
  "java.util.concurrent.atomic/AtomicLongArray/weakCompareAndSet": {
    "id": "java.util.concurrent.atomic.AtomicLongArray.weakCompareAndSet",
    "name": "weakCompareAndSet",
    "type": "method",
    "parent": "AtomicLongArray",
    "signatures": [
      "public final boolean weakCompareAndSet(int i, long expectedValue, long newValue)"
    ],
    "signature_hash": "c71af626d5ffd9c8410272b49e8a4e365080a036676ee2d6ccabf72e9499ef05",
    "url": "https://docs.oracle.com/en/java/javase/25/docs/api/java.base/java/util/concurrent/atomic/AtomicLongArray.html",
    "parameters": [
      {
        "name": "i",
        "type": "int",
        "has_default": false,
        "default_value": null,
        "is_keyword_only": false,
        "is_var_args": false,
        "is_var_kwargs": false,
        "description": ""
      },
      {
        "name": "expectedValue",
        "type": "long",
        "has_default": false,
        "default_value": null,
        "is_keyword_only": false,
        "is_var_args": false,
        "is_var_kwargs": false,
        "description": ""
      },
      {
        "name": "newValue",
        "type": "long",
        "has_default": false,
        "default_value": null,
        "is_keyword_only": false,
        "is_var_args": false,
        "is_var_kwargs": false,
        "description": ""
      }
    ],
    "return_type": "final boolean",
    "exceptions": [],
    "description": "Deprecated.This method has plain memory effects but the method\nname implies volatile memory effects (see methods such ascompareAndExchange(int, long, long)andcompareAndSet(int, long, long)).",
    "example": "",
    "articles": [],
    "info": {
      "status": "empty",
      "excerpt": "Deprecated.This method has plain memory effects but the method\nname implies volatile memory effects (see methods such ascompareAndExchange(int, long, long)andcompareAndSet(int, long, long)).",
      "keyword": "",
      "seo_position": 0,
      "visits": 0
    },
    "createdDate": "2026-03-11T23:15:40.860088",
    "updatedDate": "2026-03-11T23:15:40.860089",
    "metadata": {
      "deprecated": true,
      "deprecated_version": "unknown",
      "added_version": "1.5",
      "tags": [],
      "difficulty": null,
      "popularity_score": 0
    }
  },
  "java.util.concurrent.atomic/AtomicReferenceArray/weakCompareAndSet": {
    "id": "java.util.concurrent.atomic.AtomicReferenceArray.weakCompareAndSet",
    "name": "weakCompareAndSet",
    "type": "method",
    "parent": "AtomicReferenceArray",
    "signatures": [
      "public final boolean weakCompareAndSet(int i, E expectedValue, E newValue)"
    ],
    "signature_hash": "db0a8b863b9a006354bb9eb0774b96cc67d7258c3cfb3edaa149e27bfcf33872",
    "url": "https://docs.oracle.com/en/java/javase/25/docs/api/java.base/java/util/concurrent/atomic/AtomicReferenceArray.html",
    "parameters": [
      {
        "name": "i",
        "type": "int",
        "has_default": false,
        "default_value": null,
        "is_keyword_only": false,
        "is_var_args": false,
        "is_var_kwargs": false,
        "description": ""
      },
      {
        "name": "expectedValue",
        "type": "E",
        "has_default": false,
        "default_value": null,
        "is_keyword_only": false,
        "is_var_args": false,
        "is_var_kwargs": false,
        "description": ""
      },
      {
        "name": "newValue",
        "type": "E",
        "has_default": false,
        "default_value": null,
        "is_keyword_only": false,
        "is_var_args": false,
        "is_var_kwargs": false,
        "description": ""
      }
    ],
    "return_type": "final boolean",
    "exceptions": [],
    "description": "Deprecated.This method has plain memory effects but the method\nname implies volatile memory effects (see methods such ascompareAndExchange(int, E, E)andcompareAndSet(int, E, E)).",
    "example": "",
    "articles": [],
    "info": {
      "status": "empty",
      "excerpt": "Deprecated.This method has plain memory effects but the method\nname implies volatile memory effects (see methods such ascompareAndExchange(int, E, E)andcompareAndSet(int, E, E)).",
      "keyword": "",
      "seo_position": 0,
      "visits": 0
    },
    "createdDate": "2026-03-11T23:15:40.860907",
    "updatedDate": "2026-03-11T23:15:40.860908",
    "metadata": {
      "deprecated": true,
      "deprecated_version": "unknown",
      "added_version": "1.5",
      "tags": [],
      "difficulty": null,
      "popularity_score": 0
    }
  },
  "java.util.concurrent.atomic/AtomicReferenceFieldUpdater/weakCompareAndSet": {
    "id": "java.util.concurrent.atomic.AtomicReferenceFieldUpdater.weakCompareAndSet",
    "name": "weakCompareAndSet",
    "type": "method",
    "parent": "AtomicReferenceFieldUpdater",
    "signatures": [
      "public abstract boolean weakCompareAndSet(T obj, V expect, V update)"
    ],
    "signature_hash": "b0e8563f2273be48bbf77f713fb2f137b0a87dd0e684a9eba14c3a8dd7fde20b",
    "url": "https://docs.oracle.com/en/java/javase/25/docs/api/java.base/java/util/concurrent/atomic/AtomicReferenceFieldUpdater.html",
    "parameters": [
      {
        "name": "obj",
        "type": "T",
        "has_default": false,
        "default_value": null,
        "is_keyword_only": false,
        "is_var_args": false,
        "is_var_kwargs": false,
        "description": ""
      },
      {
        "name": "expect",
        "type": "V",
        "has_default": false,
        "default_value": null,
        "is_keyword_only": false,
        "is_var_args": false,
        "is_var_kwargs": false,
        "description": ""
      },
      {
        "name": "update",
        "type": "V",
        "has_default": false,
        "default_value": null,
        "is_keyword_only": false,
        "is_var_args": false,
        "is_var_kwargs": false,
        "description": ""
      }
    ],
    "return_type": "abstract boolean",
    "exceptions": [],
    "description": "Atomically sets the field of the given object managed by this updater\nto the given updated value if the current value==the\nexpected value.",
    "example": "",
    "articles": [],
    "info": {
      "status": "empty",
      "excerpt": "Atomically sets the field of the given object managed by this updater\nto the given updated value if the current value==the\nexpected value.",
      "keyword": "",
      "seo_position": 0,
      "visits": 0
    },
    "createdDate": "2026-03-11T23:15:40.861615",
    "updatedDate": "2026-03-11T23:15:40.861616",
    "metadata": {
      "deprecated": false,
      "deprecated_version": null,
      "added_version": "1.5",
      "tags": [],
      "difficulty": null,
      "popularity_score": 0
    }
  },
  "java.util.concurrent.atomic/AtomicIntegerFieldUpdater/weakCompareAndSet": {
    "id": "java.util.concurrent.atomic.AtomicIntegerFieldUpdater.weakCompareAndSet",
    "name": "weakCompareAndSet",
    "type": "method",
    "parent": "AtomicIntegerFieldUpdater",
    "signatures": [
      "public abstract boolean weakCompareAndSet(T obj, int expect, int update)"
    ],
    "signature_hash": "e2407a523533989a0a9c0be27f021e3e62833e7947dce7faeea2da9f04db8d68",
    "url": "https://docs.oracle.com/en/java/javase/25/docs/api/java.base/java/util/concurrent/atomic/AtomicIntegerFieldUpdater.html",
    "parameters": [
      {
        "name": "obj",
        "type": "T",
        "has_default": false,
        "default_value": null,
        "is_keyword_only": false,
        "is_var_args": false,
        "is_var_kwargs": false,
        "description": ""
      },
      {
        "name": "expect",
        "type": "int",
        "has_default": false,
        "default_value": null,
        "is_keyword_only": false,
        "is_var_args": false,
        "is_var_kwargs": false,
        "description": ""
      },
      {
        "name": "update",
        "type": "int",
        "has_default": false,
        "default_value": null,
        "is_keyword_only": false,
        "is_var_args": false,
        "is_var_kwargs": false,
        "description": ""
      }
    ],
    "return_type": "abstract boolean",
    "exceptions": [],
    "description": "Atomically sets the field of the given object managed by this updater\nto the given updated value if the current value==the\nexpected value.",
    "example": "",
    "articles": [],
    "info": {
      "status": "empty",
      "excerpt": "Atomically sets the field of the given object managed by this updater\nto the given updated value if the current value==the\nexpected value.",
      "keyword": "",
      "seo_position": 0,
      "visits": 0
    },
    "createdDate": "2026-03-11T23:15:40.862215",
    "updatedDate": "2026-03-11T23:15:40.862216",
    "metadata": {
      "deprecated": false,
      "deprecated_version": null,
      "added_version": "1.5",
      "tags": [],
      "difficulty": null,
      "popularity_score": 0
    }
  },
  "java.util.concurrent.atomic/AtomicLongFieldUpdater/weakCompareAndSet": {
    "id": "java.util.concurrent.atomic.AtomicLongFieldUpdater.weakCompareAndSet",
    "name": "weakCompareAndSet",
    "type": "method",
    "parent": "AtomicLongFieldUpdater",
    "signatures": [
      "public abstract boolean weakCompareAndSet(T obj, long expect, long update)"
    ],
    "signature_hash": "89e887f5dab28efbe067936d7cc8a4e96db81b8e630ffc455c57847317b04417",
    "url": "https://docs.oracle.com/en/java/javase/25/docs/api/java.base/java/util/concurrent/atomic/AtomicLongFieldUpdater.html",
    "parameters": [
      {
        "name": "obj",
        "type": "T",
        "has_default": false,
        "default_value": null,
        "is_keyword_only": false,
        "is_var_args": false,
        "is_var_kwargs": false,
        "description": ""
      },
      {
        "name": "expect",
        "type": "long",
        "has_default": false,
        "default_value": null,
        "is_keyword_only": false,
        "is_var_args": false,
        "is_var_kwargs": false,
        "description": ""
      },
      {
        "name": "update",
        "type": "long",
        "has_default": false,
        "default_value": null,
        "is_keyword_only": false,
        "is_var_args": false,
        "is_var_kwargs": false,
        "description": ""
      }
    ],
    "return_type": "abstract boolean",
    "exceptions": [],
    "description": "Atomically sets the field of the given object managed by this updater\nto the given updated value if the current value==the\nexpected value.",
    "example": "",
    "articles": [],
    "info": {
      "status": "empty",
      "excerpt": "Atomically sets the field of the given object managed by this updater\nto the given updated value if the current value==the\nexpected value.",
      "keyword": "",
      "seo_position": 0,
      "visits": 0
    },
    "createdDate": "2026-03-11T23:15:40.862911",
    "updatedDate": "2026-03-11T23:15:40.862912",
    "metadata": {
      "deprecated": false,
      "deprecated_version": null,
      "added_version": "1.5",
      "tags": [],
      "difficulty": null,
      "popularity_score": 0
    }
  },
  "java.util.concurrent.atomic/AtomicMarkableReference/weakCompareAndSet": {
    "id": "java.util.concurrent.atomic.AtomicMarkableReference.weakCompareAndSet",
    "name": "weakCompareAndSet",
    "type": "method",
    "parent": "AtomicMarkableReference",
    "signatures": [
      "public boolean weakCompareAndSet(V expectedReference, V newReference, boolean expectedMark, boolean newMark)"
    ],
    "signature_hash": "e8400dd0af606d121ab297e2e62c945b877863da8639cb90b620c64aad07b658",
    "url": "https://docs.oracle.com/en/java/javase/25/docs/api/java.base/java/util/concurrent/atomic/AtomicMarkableReference.html",
    "parameters": [
      {
        "name": "expectedReference",
        "type": "V",
        "has_default": false,
        "default_value": null,
        "is_keyword_only": false,
        "is_var_args": false,
        "is_var_kwargs": false,
        "description": ""
      },
      {
        "name": "newReference",
        "type": "V",
        "has_default": false,
        "default_value": null,
        "is_keyword_only": false,
        "is_var_args": false,
        "is_var_kwargs": false,
        "description": ""
      },
      {
        "name": "expectedMark",
        "type": "boolean",
        "has_default": false,
        "default_value": null,
        "is_keyword_only": false,
        "is_var_args": false,
        "is_var_kwargs": false,
        "description": ""
      },
      {
        "name": "newMark",
        "type": "boolean",
        "has_default": false,
        "default_value": null,
        "is_keyword_only": false,
        "is_var_args": false,
        "is_var_kwargs": false,
        "description": ""
      }
    ],
    "return_type": "boolean",
    "exceptions": [],
    "description": "Atomically sets the value of both the reference and mark to the\ngiven update values if the current reference is==to\nthe expected reference and the current mark is equal to the\nexpected mark.",
    "example": "",
    "articles": [],
    "info": {
      "status": "empty",
      "excerpt": "Atomically sets the value of both the reference and mark to the\ngiven update values if the current reference is==to\nthe expected reference and the current mark is equal to the\nexpected mark.",
      "keyword": "",
      "seo_position": 0,
      "visits": 0
    },
    "createdDate": "2026-03-11T23:15:40.863196",
    "updatedDate": "2026-03-11T23:15:40.863197",
    "metadata": {
      "deprecated": false,
      "deprecated_version": null,
      "added_version": "1.5",
      "tags": [],
      "difficulty": null,
      "popularity_score": 0
    }
  },
  "java.util.concurrent.atomic/AtomicStampedReference/weakCompareAndSet": {
    "id": "java.util.concurrent.atomic.AtomicStampedReference.weakCompareAndSet",
    "name": "weakCompareAndSet",
    "type": "method",
    "parent": "AtomicStampedReference",
    "signatures": [
      "public boolean weakCompareAndSet(V expectedReference, V newReference, int expectedStamp, int newStamp)"
    ],
    "signature_hash": "998d860b2e5b23d819a86ddc08fee1cc0b790d8ee1081ef84a70b0cdea26043b",
    "url": "https://docs.oracle.com/en/java/javase/25/docs/api/java.base/java/util/concurrent/atomic/AtomicStampedReference.html",
    "parameters": [
      {
        "name": "expectedReference",
        "type": "V",
        "has_default": false,
        "default_value": null,
        "is_keyword_only": false,
        "is_var_args": false,
        "is_var_kwargs": false,
        "description": ""
      },
      {
        "name": "newReference",
        "type": "V",
        "has_default": false,
        "default_value": null,
        "is_keyword_only": false,
        "is_var_args": false,
        "is_var_kwargs": false,
        "description": ""
      },
      {
        "name": "expectedStamp",
        "type": "int",
        "has_default": false,
        "default_value": null,
        "is_keyword_only": false,
        "is_var_args": false,
        "is_var_kwargs": false,
        "description": ""
      },
      {
        "name": "newStamp",
        "type": "int",
        "has_default": false,
        "default_value": null,
        "is_keyword_only": false,
        "is_var_args": false,
        "is_var_kwargs": false,
        "description": ""
      }
    ],
    "return_type": "boolean",
    "exceptions": [],
    "description": "Atomically sets the value of both the reference and stamp to\nthe given update values if the current reference is==to the expected reference and the current stamp is equal to the\nexpected stamp.",
    "example": "",
    "articles": [],
    "info": {
      "status": "empty",
      "excerpt": "Atomically sets the value of both the reference and stamp to\nthe given update values if the current reference is==to the expected reference and the current stamp is equal to the\nexpected stamp.",
      "keyword": "",
      "seo_position": 0,
      "visits": 0
    },
    "createdDate": "2026-03-11T23:15:40.863466",
    "updatedDate": "2026-03-11T23:15:40.863467",
    "metadata": {
      "deprecated": false,
      "deprecated_version": null,
      "added_version": "1.5",
      "tags": [],
      "difficulty": null,
      "popularity_score": 0
    }
  },
  "java.util.concurrent.atomic/AtomicBoolean/weakCompareAndSetAcquire": {
    "id": "java.util.concurrent.atomic.AtomicBoolean.weakCompareAndSetAcquire",
    "name": "weakCompareAndSetAcquire",
    "type": "method",
    "parent": "AtomicBoolean",
    "signatures": [
      "public final boolean weakCompareAndSetAcquire(boolean expectedValue, boolean newValue)"
    ],
    "signature_hash": "ec1df254f185cdcac5c71f69475664361c5bb93d4ae459198fb0c3715016b339",
    "url": "https://docs.oracle.com/en/java/javase/25/docs/api/java.base/java/util/concurrent/atomic/AtomicBoolean.html",
    "parameters": [
      {
        "name": "expectedValue",
        "type": "boolean",
        "has_default": false,
        "default_value": null,
        "is_keyword_only": false,
        "is_var_args": false,
        "is_var_kwargs": false,
        "description": ""
      },
      {
        "name": "newValue",
        "type": "boolean",
        "has_default": false,
        "default_value": null,
        "is_keyword_only": false,
        "is_var_args": false,
        "is_var_kwargs": false,
        "description": ""
      }
    ],
    "return_type": "final boolean",
    "exceptions": [],
    "description": "Possibly atomically sets the value tonewValueif the current\nvalue== expectedValue,\nwith memory effects as specified byVarHandle.weakCompareAndSetAcquire(Object...).",
    "example": "",
    "articles": [],
    "info": {
      "status": "empty",
      "excerpt": "Possibly atomically sets the value tonewValueif the current\nvalue== expectedValue,\nwith memory effects as specified byVarHandle.weakCompareAndSetAcquire(Object...).",
      "keyword": "",
      "seo_position": 0,
      "visits": 0
    },
    "createdDate": "2026-03-11T23:15:40.855486",
    "updatedDate": "2026-03-11T23:15:40.855487",
    "metadata": {
      "deprecated": true,
      "deprecated_version": "unknown",
      "added_version": "1.5",
      "tags": [],
      "difficulty": null,
      "popularity_score": 0
    }
  },
  "java.util.concurrent.atomic/AtomicInteger/weakCompareAndSetAcquire": {
    "id": "java.util.concurrent.atomic.AtomicInteger.weakCompareAndSetAcquire",
    "name": "weakCompareAndSetAcquire",
    "type": "method",
    "parent": "AtomicInteger",
    "signatures": [
      "public final boolean weakCompareAndSetAcquire(int expectedValue, int newValue)"
    ],
    "signature_hash": "b67eaa3b67754349ed43b61bc0c6947d9347c0bd19938fc53b86ca1246241c0b",
    "url": "https://docs.oracle.com/en/java/javase/25/docs/api/java.base/java/util/concurrent/atomic/AtomicInteger.html",
    "parameters": [
      {
        "name": "expectedValue",
        "type": "int",
        "has_default": false,
        "default_value": null,
        "is_keyword_only": false,
        "is_var_args": false,
        "is_var_kwargs": false,
        "description": ""
      },
      {
        "name": "newValue",
        "type": "int",
        "has_default": false,
        "default_value": null,
        "is_keyword_only": false,
        "is_var_args": false,
        "is_var_kwargs": false,
        "description": ""
      }
    ],
    "return_type": "final boolean",
    "exceptions": [],
    "description": "Possibly atomically sets the value tonewValueif\nthe current value== expectedValue,\nwith memory effects as specified byVarHandle.weakCompareAndSetAcquire(Object...).",
    "example": "",
    "articles": [],
    "info": {
      "status": "empty",
      "excerpt": "Possibly atomically sets the value tonewValueif\nthe current value== expectedValue,\nwith memory effects as specified byVarHandle.weakCompareAndSetAcquire(Object...).",
      "keyword": "",
      "seo_position": 0,
      "visits": 0
    },
    "createdDate": "2026-03-11T23:15:40.856658",
    "updatedDate": "2026-03-11T23:15:40.856659",
    "metadata": {
      "deprecated": true,
      "deprecated_version": "unknown",
      "added_version": "1.5",
      "tags": [],
      "difficulty": null,
      "popularity_score": 0
    }
  },
  "java.util.concurrent.atomic/AtomicLong/weakCompareAndSetAcquire": {
    "id": "java.util.concurrent.atomic.AtomicLong.weakCompareAndSetAcquire",
    "name": "weakCompareAndSetAcquire",
    "type": "method",
    "parent": "AtomicLong",
    "signatures": [
      "public final boolean weakCompareAndSetAcquire(long expectedValue, long newValue)"
    ],
    "signature_hash": "361c84e9bcf2a1f50fc8b95c9930a3b53eb5552125a0cd770ea7a86c638d9ebe",
    "url": "https://docs.oracle.com/en/java/javase/25/docs/api/java.base/java/util/concurrent/atomic/AtomicLong.html",
    "parameters": [
      {
        "name": "expectedValue",
        "type": "long",
        "has_default": false,
        "default_value": null,
        "is_keyword_only": false,
        "is_var_args": false,
        "is_var_kwargs": false,
        "description": ""
      },
      {
        "name": "newValue",
        "type": "long",
        "has_default": false,
        "default_value": null,
        "is_keyword_only": false,
        "is_var_args": false,
        "is_var_kwargs": false,
        "description": ""
      }
    ],
    "return_type": "final boolean",
    "exceptions": [],
    "description": "Possibly atomically sets the value tonewValueif the current value== expectedValue,\nwith memory effects as specified byVarHandle.weakCompareAndSetAcquire(Object...).",
    "example": "",
    "articles": [],
    "info": {
      "status": "empty",
      "excerpt": "Possibly atomically sets the value tonewValueif the current value== expectedValue,\nwith memory effects as specified byVarHandle.weakCompareAndSetAcquire(Object...).",
      "keyword": "",
      "seo_position": 0,
      "visits": 0
    },
    "createdDate": "2026-03-11T23:15:40.857564",
    "updatedDate": "2026-03-11T23:15:40.857565",
    "metadata": {
      "deprecated": true,
      "deprecated_version": "unknown",
      "added_version": "1.5",
      "tags": [],
      "difficulty": null,
      "popularity_score": 0
    }
  },
  "java.util.concurrent.atomic/AtomicReference/weakCompareAndSetAcquire": {
    "id": "java.util.concurrent.atomic.AtomicReference.weakCompareAndSetAcquire",
    "name": "weakCompareAndSetAcquire",
    "type": "method",
    "parent": "AtomicReference",
    "signatures": [
      "public final boolean weakCompareAndSetAcquire(V expectedValue, V newValue)"
    ],
    "signature_hash": "a7b935b48db6159b21994c738d6dd686d24ff6fe79a210fdac9db65c50621b80",
    "url": "https://docs.oracle.com/en/java/javase/25/docs/api/java.base/java/util/concurrent/atomic/AtomicReference.html",
    "parameters": [
      {
        "name": "expectedValue",
        "type": "V",
        "has_default": false,
        "default_value": null,
        "is_keyword_only": false,
        "is_var_args": false,
        "is_var_kwargs": false,
        "description": ""
      },
      {
        "name": "newValue",
        "type": "V",
        "has_default": false,
        "default_value": null,
        "is_keyword_only": false,
        "is_var_args": false,
        "is_var_kwargs": false,
        "description": ""
      }
    ],
    "return_type": "final boolean",
    "exceptions": [],
    "description": "Possibly atomically sets the value tonewValueif the current value== expectedValue,\nwith memory effects as specified byVarHandle.weakCompareAndSetAcquire(Object...).",
    "example": "",
    "articles": [],
    "info": {
      "status": "empty",
      "excerpt": "Possibly atomically sets the value tonewValueif the current value== expectedValue,\nwith memory effects as specified byVarHandle.weakCompareAndSetAcquire(Object...).",
      "keyword": "",
      "seo_position": 0,
      "visits": 0
    },
    "createdDate": "2026-03-11T23:15:40.858204",
    "updatedDate": "2026-03-11T23:15:40.858205",
    "metadata": {
      "deprecated": true,
      "deprecated_version": "unknown",
      "added_version": "1.5",
      "tags": [],
      "difficulty": null,
      "popularity_score": 0
    }
  },
  "java.util.concurrent.atomic/AtomicIntegerArray/weakCompareAndSetAcquire": {
    "id": "java.util.concurrent.atomic.AtomicIntegerArray.weakCompareAndSetAcquire",
    "name": "weakCompareAndSetAcquire",
    "type": "method",
    "parent": "AtomicIntegerArray",
    "signatures": [
      "public final boolean weakCompareAndSetAcquire(int i, int expectedValue, int newValue)"
    ],
    "signature_hash": "83bc02ac92471b7d20b1379a915ac7b97142b51afaca9f9b7acda1b8495865d1",
    "url": "https://docs.oracle.com/en/java/javase/25/docs/api/java.base/java/util/concurrent/atomic/AtomicIntegerArray.html",
    "parameters": [
      {
        "name": "i",
        "type": "int",
        "has_default": false,
        "default_value": null,
        "is_keyword_only": false,
        "is_var_args": false,
        "is_var_kwargs": false,
        "description": ""
      },
      {
        "name": "expectedValue",
        "type": "int",
        "has_default": false,
        "default_value": null,
        "is_keyword_only": false,
        "is_var_args": false,
        "is_var_kwargs": false,
        "description": ""
      },
      {
        "name": "newValue",
        "type": "int",
        "has_default": false,
        "default_value": null,
        "is_keyword_only": false,
        "is_var_args": false,
        "is_var_kwargs": false,
        "description": ""
      }
    ],
    "return_type": "final boolean",
    "exceptions": [],
    "description": "Possibly atomically sets the element at indexitonewValueif the element's current value== expectedValue,\nwith memory effects as specified byVarHandle.weakCompareAndSetAcquire(Object...).",
    "example": "",
    "articles": [],
    "info": {
      "status": "empty",
      "excerpt": "Possibly atomically sets the element at indexitonewValueif the element's current value== expectedValue,\nwith memory effects as specified byVarHandle.weakCompareAndSetAcquire(Object...).",
      "keyword": "",
      "seo_position": 0,
      "visits": 0
    },
    "createdDate": "2026-03-11T23:15:40.859086",
    "updatedDate": "2026-03-11T23:15:40.859087",
    "metadata": {
      "deprecated": true,
      "deprecated_version": "unknown",
      "added_version": "1.5",
      "tags": [],
      "difficulty": null,
      "popularity_score": 0
    }
  },
  "java.util.concurrent.atomic/AtomicLongArray/weakCompareAndSetAcquire": {
    "id": "java.util.concurrent.atomic.AtomicLongArray.weakCompareAndSetAcquire",
    "name": "weakCompareAndSetAcquire",
    "type": "method",
    "parent": "AtomicLongArray",
    "signatures": [
      "public final boolean weakCompareAndSetAcquire(int i, long expectedValue, long newValue)"
    ],
    "signature_hash": "2d93dac143b706b48d975a5124708ef37f4699faa87cd22e4c59380956f811e4",
    "url": "https://docs.oracle.com/en/java/javase/25/docs/api/java.base/java/util/concurrent/atomic/AtomicLongArray.html",
    "parameters": [
      {
        "name": "i",
        "type": "int",
        "has_default": false,
        "default_value": null,
        "is_keyword_only": false,
        "is_var_args": false,
        "is_var_kwargs": false,
        "description": ""
      },
      {
        "name": "expectedValue",
        "type": "long",
        "has_default": false,
        "default_value": null,
        "is_keyword_only": false,
        "is_var_args": false,
        "is_var_kwargs": false,
        "description": ""
      },
      {
        "name": "newValue",
        "type": "long",
        "has_default": false,
        "default_value": null,
        "is_keyword_only": false,
        "is_var_args": false,
        "is_var_kwargs": false,
        "description": ""
      }
    ],
    "return_type": "final boolean",
    "exceptions": [],
    "description": "Possibly atomically sets the element at indexitonewValueif the element's current value== expectedValue,\nwith memory effects as specified byVarHandle.weakCompareAndSetAcquire(Object...).",
    "example": "",
    "articles": [],
    "info": {
      "status": "empty",
      "excerpt": "Possibly atomically sets the element at indexitonewValueif the element's current value== expectedValue,\nwith memory effects as specified byVarHandle.weakCompareAndSetAcquire(Object...).",
      "keyword": "",
      "seo_position": 0,
      "visits": 0
    },
    "createdDate": "2026-03-11T23:15:40.860117",
    "updatedDate": "2026-03-11T23:15:40.860118",
    "metadata": {
      "deprecated": true,
      "deprecated_version": "unknown",
      "added_version": "1.5",
      "tags": [],
      "difficulty": null,
      "popularity_score": 0
    }
  },
  "java.util.concurrent.atomic/AtomicReferenceArray/weakCompareAndSetAcquire": {
    "id": "java.util.concurrent.atomic.AtomicReferenceArray.weakCompareAndSetAcquire",
    "name": "weakCompareAndSetAcquire",
    "type": "method",
    "parent": "AtomicReferenceArray",
    "signatures": [
      "public final boolean weakCompareAndSetAcquire(int i, E expectedValue, E newValue)"
    ],
    "signature_hash": "bb20b93c8afd0638d19a288f6bbee073b30b871febe684cc414e93d6d511169c",
    "url": "https://docs.oracle.com/en/java/javase/25/docs/api/java.base/java/util/concurrent/atomic/AtomicReferenceArray.html",
    "parameters": [
      {
        "name": "i",
        "type": "int",
        "has_default": false,
        "default_value": null,
        "is_keyword_only": false,
        "is_var_args": false,
        "is_var_kwargs": false,
        "description": ""
      },
      {
        "name": "expectedValue",
        "type": "E",
        "has_default": false,
        "default_value": null,
        "is_keyword_only": false,
        "is_var_args": false,
        "is_var_kwargs": false,
        "description": ""
      },
      {
        "name": "newValue",
        "type": "E",
        "has_default": false,
        "default_value": null,
        "is_keyword_only": false,
        "is_var_args": false,
        "is_var_kwargs": false,
        "description": ""
      }
    ],
    "return_type": "final boolean",
    "exceptions": [],
    "description": "Possibly atomically sets the element at indexitonewValueif the element's current value== expectedValue,\nwith memory effects as specified byVarHandle.weakCompareAndSetAcquire(Object...).",
    "example": "",
    "articles": [],
    "info": {
      "status": "empty",
      "excerpt": "Possibly atomically sets the element at indexitonewValueif the element's current value== expectedValue,\nwith memory effects as specified byVarHandle.weakCompareAndSetAcquire(Object...).",
      "keyword": "",
      "seo_position": 0,
      "visits": 0
    },
    "createdDate": "2026-03-11T23:15:40.860936",
    "updatedDate": "2026-03-11T23:15:40.860937",
    "metadata": {
      "deprecated": true,
      "deprecated_version": "unknown",
      "added_version": "1.5",
      "tags": [],
      "difficulty": null,
      "popularity_score": 0
    }
  },
  "java.util.concurrent.atomic/AtomicBoolean/weakCompareAndSetPlain": {
    "id": "java.util.concurrent.atomic.AtomicBoolean.weakCompareAndSetPlain",
    "name": "weakCompareAndSetPlain",
    "type": "method",
    "parent": "AtomicBoolean",
    "signatures": [
      "public boolean weakCompareAndSetPlain(boolean expectedValue, boolean newValue)"
    ],
    "signature_hash": "65da4f8739fd1079322b6fbfc780e46284b109e76e9ee7a3b67034177fe4a427",
    "url": "https://docs.oracle.com/en/java/javase/25/docs/api/java.base/java/util/concurrent/atomic/AtomicBoolean.html",
    "parameters": [
      {
        "name": "expectedValue",
        "type": "boolean",
        "has_default": false,
        "default_value": null,
        "is_keyword_only": false,
        "is_var_args": false,
        "is_var_kwargs": false,
        "description": ""
      },
      {
        "name": "newValue",
        "type": "boolean",
        "has_default": false,
        "default_value": null,
        "is_keyword_only": false,
        "is_var_args": false,
        "is_var_kwargs": false,
        "description": ""
      }
    ],
    "return_type": "boolean",
    "exceptions": [],
    "description": "Possibly atomically sets the value tonewValueif the current value== expectedValue,\nwith memory effects as specified byVarHandle.weakCompareAndSetPlain(Object...).",
    "example": "",
    "articles": [],
    "info": {
      "status": "empty",
      "excerpt": "Possibly atomically sets the value tonewValueif the current value== expectedValue,\nwith memory effects as specified byVarHandle.weakCompareAndSetPlain(Object...).",
      "keyword": "",
      "seo_position": 0,
      "visits": 0
    },
    "createdDate": "2026-03-11T23:15:40.855542",
    "updatedDate": "2026-03-11T23:15:40.855543",
    "metadata": {
      "deprecated": true,
      "deprecated_version": "unknown",
      "added_version": "1.5",
      "tags": [],
      "difficulty": null,
      "popularity_score": 0
    }
  },
  "java.util.concurrent.atomic/AtomicInteger/weakCompareAndSetPlain": {
    "id": "java.util.concurrent.atomic.AtomicInteger.weakCompareAndSetPlain",
    "name": "weakCompareAndSetPlain",
    "type": "method",
    "parent": "AtomicInteger",
    "signatures": [
      "public final boolean weakCompareAndSetPlain(int expectedValue, int newValue)"
    ],
    "signature_hash": "1f1b9d02da2ceb1070568cc16f49a5e0263ccbe484e0deefeb115bb181b85f41",
    "url": "https://docs.oracle.com/en/java/javase/25/docs/api/java.base/java/util/concurrent/atomic/AtomicInteger.html",
    "parameters": [
      {
        "name": "expectedValue",
        "type": "int",
        "has_default": false,
        "default_value": null,
        "is_keyword_only": false,
        "is_var_args": false,
        "is_var_kwargs": false,
        "description": ""
      },
      {
        "name": "newValue",
        "type": "int",
        "has_default": false,
        "default_value": null,
        "is_keyword_only": false,
        "is_var_args": false,
        "is_var_kwargs": false,
        "description": ""
      }
    ],
    "return_type": "final boolean",
    "exceptions": [],
    "description": "Possibly atomically sets the value tonewValueif the current value== expectedValue,\nwith memory effects as specified byVarHandle.weakCompareAndSetPlain(Object...).",
    "example": "",
    "articles": [],
    "info": {
      "status": "empty",
      "excerpt": "Possibly atomically sets the value tonewValueif the current value== expectedValue,\nwith memory effects as specified byVarHandle.weakCompareAndSetPlain(Object...).",
      "keyword": "",
      "seo_position": 0,
      "visits": 0
    },
    "createdDate": "2026-03-11T23:15:40.856680",
    "updatedDate": "2026-03-11T23:15:40.856681",
    "metadata": {
      "deprecated": true,
      "deprecated_version": "unknown",
      "added_version": "1.5",
      "tags": [],
      "difficulty": null,
      "popularity_score": 0
    }
  },
  "java.util.concurrent.atomic/AtomicLong/weakCompareAndSetPlain": {
    "id": "java.util.concurrent.atomic.AtomicLong.weakCompareAndSetPlain",
    "name": "weakCompareAndSetPlain",
    "type": "method",
    "parent": "AtomicLong",
    "signatures": [
      "public final boolean weakCompareAndSetPlain(long expectedValue, long newValue)"
    ],
    "signature_hash": "5854f9bbd9a5932d1d91821d05e2e02c180be20b2c9d9c1f16b5a9086e41d2da",
    "url": "https://docs.oracle.com/en/java/javase/25/docs/api/java.base/java/util/concurrent/atomic/AtomicLong.html",
    "parameters": [
      {
        "name": "expectedValue",
        "type": "long",
        "has_default": false,
        "default_value": null,
        "is_keyword_only": false,
        "is_var_args": false,
        "is_var_kwargs": false,
        "description": ""
      },
      {
        "name": "newValue",
        "type": "long",
        "has_default": false,
        "default_value": null,
        "is_keyword_only": false,
        "is_var_args": false,
        "is_var_kwargs": false,
        "description": ""
      }
    ],
    "return_type": "final boolean",
    "exceptions": [],
    "description": "Possibly atomically sets the value tonewValueif the current value== expectedValue,\nwith memory effects as specified byVarHandle.weakCompareAndSetPlain(Object...).",
    "example": "",
    "articles": [],
    "info": {
      "status": "empty",
      "excerpt": "Possibly atomically sets the value tonewValueif the current value== expectedValue,\nwith memory effects as specified byVarHandle.weakCompareAndSetPlain(Object...).",
      "keyword": "",
      "seo_position": 0,
      "visits": 0
    },
    "createdDate": "2026-03-11T23:15:40.857587",
    "updatedDate": "2026-03-11T23:15:40.857588",
    "metadata": {
      "deprecated": true,
      "deprecated_version": "unknown",
      "added_version": "1.5",
      "tags": [],
      "difficulty": null,
      "popularity_score": 0
    }
  },
  "java.util.concurrent.atomic/AtomicReference/weakCompareAndSetPlain": {
    "id": "java.util.concurrent.atomic.AtomicReference.weakCompareAndSetPlain",
    "name": "weakCompareAndSetPlain",
    "type": "method",
    "parent": "AtomicReference",
    "signatures": [
      "public final boolean weakCompareAndSetPlain(V expectedValue, V newValue)"
    ],
    "signature_hash": "12c6bbab970d75e882a373e3c7e4cd77c405ff62a244cf428375ea26d67c5620",
    "url": "https://docs.oracle.com/en/java/javase/25/docs/api/java.base/java/util/concurrent/atomic/AtomicReference.html",
    "parameters": [
      {
        "name": "expectedValue",
        "type": "V",
        "has_default": false,
        "default_value": null,
        "is_keyword_only": false,
        "is_var_args": false,
        "is_var_kwargs": false,
        "description": ""
      },
      {
        "name": "newValue",
        "type": "V",
        "has_default": false,
        "default_value": null,
        "is_keyword_only": false,
        "is_var_args": false,
        "is_var_kwargs": false,
        "description": ""
      }
    ],
    "return_type": "final boolean",
    "exceptions": [],
    "description": "Possibly atomically sets the value tonewValueif the current value== expectedValue,\nwith memory effects as specified byVarHandle.weakCompareAndSetPlain(Object...).",
    "example": "",
    "articles": [],
    "info": {
      "status": "empty",
      "excerpt": "Possibly atomically sets the value tonewValueif the current value== expectedValue,\nwith memory effects as specified byVarHandle.weakCompareAndSetPlain(Object...).",
      "keyword": "",
      "seo_position": 0,
      "visits": 0
    },
    "createdDate": "2026-03-11T23:15:40.858227",
    "updatedDate": "2026-03-11T23:15:40.858227",
    "metadata": {
      "deprecated": true,
      "deprecated_version": "unknown",
      "added_version": "1.5",
      "tags": [],
      "difficulty": null,
      "popularity_score": 0
    }
  },
  "java.util.concurrent.atomic/AtomicIntegerArray/weakCompareAndSetPlain": {
    "id": "java.util.concurrent.atomic.AtomicIntegerArray.weakCompareAndSetPlain",
    "name": "weakCompareAndSetPlain",
    "type": "method",
    "parent": "AtomicIntegerArray",
    "signatures": [
      "public final boolean weakCompareAndSetPlain(int i, int expectedValue, int newValue)"
    ],
    "signature_hash": "20b5e0c63f134b5475d74a234c0a02d21879e8583d76f417322b52bca9946ae4",
    "url": "https://docs.oracle.com/en/java/javase/25/docs/api/java.base/java/util/concurrent/atomic/AtomicIntegerArray.html",
    "parameters": [
      {
        "name": "i",
        "type": "int",
        "has_default": false,
        "default_value": null,
        "is_keyword_only": false,
        "is_var_args": false,
        "is_var_kwargs": false,
        "description": ""
      },
      {
        "name": "expectedValue",
        "type": "int",
        "has_default": false,
        "default_value": null,
        "is_keyword_only": false,
        "is_var_args": false,
        "is_var_kwargs": false,
        "description": ""
      },
      {
        "name": "newValue",
        "type": "int",
        "has_default": false,
        "default_value": null,
        "is_keyword_only": false,
        "is_var_args": false,
        "is_var_kwargs": false,
        "description": ""
      }
    ],
    "return_type": "final boolean",
    "exceptions": [],
    "description": "Possibly atomically sets the element at indexitonewValueif the element's current value== expectedValue,\nwith memory effects as specified byVarHandle.weakCompareAndSetPlain(Object...).",
    "example": "",
    "articles": [],
    "info": {
      "status": "empty",
      "excerpt": "Possibly atomically sets the element at indexitonewValueif the element's current value== expectedValue,\nwith memory effects as specified byVarHandle.weakCompareAndSetPlain(Object...).",
      "keyword": "",
      "seo_position": 0,
      "visits": 0
    },
    "createdDate": "2026-03-11T23:15:40.859148",
    "updatedDate": "2026-03-11T23:15:40.859153",
    "metadata": {
      "deprecated": true,
      "deprecated_version": "unknown",
      "added_version": "1.5",
      "tags": [],
      "difficulty": null,
      "popularity_score": 0
    }
  },
  "java.util.concurrent.atomic/AtomicLongArray/weakCompareAndSetPlain": {
    "id": "java.util.concurrent.atomic.AtomicLongArray.weakCompareAndSetPlain",
    "name": "weakCompareAndSetPlain",
    "type": "method",
    "parent": "AtomicLongArray",
    "signatures": [
      "public final boolean weakCompareAndSetPlain(int i, long expectedValue, long newValue)"
    ],
    "signature_hash": "3864c8b3e20d6a7824d0ad3cbf3ce4b772ce265a6863faf0ef4e835a5e9c35d0",
    "url": "https://docs.oracle.com/en/java/javase/25/docs/api/java.base/java/util/concurrent/atomic/AtomicLongArray.html",
    "parameters": [
      {
        "name": "i",
        "type": "int",
        "has_default": false,
        "default_value": null,
        "is_keyword_only": false,
        "is_var_args": false,
        "is_var_kwargs": false,
        "description": ""
      },
      {
        "name": "expectedValue",
        "type": "long",
        "has_default": false,
        "default_value": null,
        "is_keyword_only": false,
        "is_var_args": false,
        "is_var_kwargs": false,
        "description": ""
      },
      {
        "name": "newValue",
        "type": "long",
        "has_default": false,
        "default_value": null,
        "is_keyword_only": false,
        "is_var_args": false,
        "is_var_kwargs": false,
        "description": ""
      }
    ],
    "return_type": "final boolean",
    "exceptions": [],
    "description": "Possibly atomically sets the element at indexitonewValueif the element's current value== expectedValue,\nwith memory effects as specified byVarHandle.weakCompareAndSetPlain(Object...).",
    "example": "",
    "articles": [],
    "info": {
      "status": "empty",
      "excerpt": "Possibly atomically sets the element at indexitonewValueif the element's current value== expectedValue,\nwith memory effects as specified byVarHandle.weakCompareAndSetPlain(Object...).",
      "keyword": "",
      "seo_position": 0,
      "visits": 0
    },
    "createdDate": "2026-03-11T23:15:40.860145",
    "updatedDate": "2026-03-11T23:15:40.860146",
    "metadata": {
      "deprecated": true,
      "deprecated_version": "unknown",
      "added_version": "1.5",
      "tags": [],
      "difficulty": null,
      "popularity_score": 0
    }
  },
  "java.util.concurrent.atomic/AtomicReferenceArray/weakCompareAndSetPlain": {
    "id": "java.util.concurrent.atomic.AtomicReferenceArray.weakCompareAndSetPlain",
    "name": "weakCompareAndSetPlain",
    "type": "method",
    "parent": "AtomicReferenceArray",
    "signatures": [
      "public final boolean weakCompareAndSetPlain(int i, E expectedValue, E newValue)"
    ],
    "signature_hash": "c6559efa57a584cf3521f904186e1ce7cf974662e8d89067cd4464df43bbdfde",
    "url": "https://docs.oracle.com/en/java/javase/25/docs/api/java.base/java/util/concurrent/atomic/AtomicReferenceArray.html",
    "parameters": [
      {
        "name": "i",
        "type": "int",
        "has_default": false,
        "default_value": null,
        "is_keyword_only": false,
        "is_var_args": false,
        "is_var_kwargs": false,
        "description": ""
      },
      {
        "name": "expectedValue",
        "type": "E",
        "has_default": false,
        "default_value": null,
        "is_keyword_only": false,
        "is_var_args": false,
        "is_var_kwargs": false,
        "description": ""
      },
      {
        "name": "newValue",
        "type": "E",
        "has_default": false,
        "default_value": null,
        "is_keyword_only": false,
        "is_var_args": false,
        "is_var_kwargs": false,
        "description": ""
      }
    ],
    "return_type": "final boolean",
    "exceptions": [],
    "description": "Possibly atomically sets the element at indexitonewValueif the element's current value== expectedValue,\nwith memory effects as specified byVarHandle.weakCompareAndSetPlain(Object...).",
    "example": "",
    "articles": [],
    "info": {
      "status": "empty",
      "excerpt": "Possibly atomically sets the element at indexitonewValueif the element's current value== expectedValue,\nwith memory effects as specified byVarHandle.weakCompareAndSetPlain(Object...).",
      "keyword": "",
      "seo_position": 0,
      "visits": 0
    },
    "createdDate": "2026-03-11T23:15:40.861020",
    "updatedDate": "2026-03-11T23:15:40.861022",
    "metadata": {
      "deprecated": true,
      "deprecated_version": "unknown",
      "added_version": "1.5",
      "tags": [],
      "difficulty": null,
      "popularity_score": 0
    }
  },
  "java.util.concurrent.atomic/AtomicBoolean/weakCompareAndSetRelease": {
    "id": "java.util.concurrent.atomic.AtomicBoolean.weakCompareAndSetRelease",
    "name": "weakCompareAndSetRelease",
    "type": "method",
    "parent": "AtomicBoolean",
    "signatures": [
      "public final boolean weakCompareAndSetRelease(boolean expectedValue, boolean newValue)"
    ],
    "signature_hash": "0a34b60a7ac3bc49644844e756bfffca08fd618e7165dc498f90f43d37d0265e",
    "url": "https://docs.oracle.com/en/java/javase/25/docs/api/java.base/java/util/concurrent/atomic/AtomicBoolean.html",
    "parameters": [
      {
        "name": "expectedValue",
        "type": "boolean",
        "has_default": false,
        "default_value": null,
        "is_keyword_only": false,
        "is_var_args": false,
        "is_var_kwargs": false,
        "description": ""
      },
      {
        "name": "newValue",
        "type": "boolean",
        "has_default": false,
        "default_value": null,
        "is_keyword_only": false,
        "is_var_args": false,
        "is_var_kwargs": false,
        "description": ""
      }
    ],
    "return_type": "final boolean",
    "exceptions": [],
    "description": "Possibly atomically sets the value tonewValueif the current\nvalue== expectedValue,\nwith memory effects as specified byVarHandle.weakCompareAndSetRelease(Object...).",
    "example": "",
    "articles": [],
    "info": {
      "status": "empty",
      "excerpt": "Possibly atomically sets the value tonewValueif the current\nvalue== expectedValue,\nwith memory effects as specified byVarHandle.weakCompareAndSetRelease(Object...).",
      "keyword": "",
      "seo_position": 0,
      "visits": 0
    },
    "createdDate": "2026-03-11T23:15:40.855574",
    "updatedDate": "2026-03-11T23:15:40.855575",
    "metadata": {
      "deprecated": true,
      "deprecated_version": "unknown",
      "added_version": "1.5",
      "tags": [],
      "difficulty": null,
      "popularity_score": 0
    }
  },
  "java.util.concurrent.atomic/AtomicInteger/weakCompareAndSetRelease": {
    "id": "java.util.concurrent.atomic.AtomicInteger.weakCompareAndSetRelease",
    "name": "weakCompareAndSetRelease",
    "type": "method",
    "parent": "AtomicInteger",
    "signatures": [
      "public final boolean weakCompareAndSetRelease(int expectedValue, int newValue)"
    ],
    "signature_hash": "dd5cc56037cf993a01d3eba66e76da8224c44c36e300bda0c64d62ef34bf0029",
    "url": "https://docs.oracle.com/en/java/javase/25/docs/api/java.base/java/util/concurrent/atomic/AtomicInteger.html",
    "parameters": [
      {
        "name": "expectedValue",
        "type": "int",
        "has_default": false,
        "default_value": null,
        "is_keyword_only": false,
        "is_var_args": false,
        "is_var_kwargs": false,
        "description": ""
      },
      {
        "name": "newValue",
        "type": "int",
        "has_default": false,
        "default_value": null,
        "is_keyword_only": false,
        "is_var_args": false,
        "is_var_kwargs": false,
        "description": ""
      }
    ],
    "return_type": "final boolean",
    "exceptions": [],
    "description": "Possibly atomically sets the value tonewValueif\nthe current value== expectedValue,\nwith memory effects as specified byVarHandle.weakCompareAndSetRelease(Object...).",
    "example": "",
    "articles": [],
    "info": {
      "status": "empty",
      "excerpt": "Possibly atomically sets the value tonewValueif\nthe current value== expectedValue,\nwith memory effects as specified byVarHandle.weakCompareAndSetRelease(Object...).",
      "keyword": "",
      "seo_position": 0,
      "visits": 0
    },
    "createdDate": "2026-03-11T23:15:40.856701",
    "updatedDate": "2026-03-11T23:15:40.856702",
    "metadata": {
      "deprecated": true,
      "deprecated_version": "unknown",
      "added_version": "1.5",
      "tags": [],
      "difficulty": null,
      "popularity_score": 0
    }
  },
  "java.util.concurrent.atomic/AtomicLong/weakCompareAndSetRelease": {
    "id": "java.util.concurrent.atomic.AtomicLong.weakCompareAndSetRelease",
    "name": "weakCompareAndSetRelease",
    "type": "method",
    "parent": "AtomicLong",
    "signatures": [
      "public final boolean weakCompareAndSetRelease(long expectedValue, long newValue)"
    ],
    "signature_hash": "a6424d19986c35667a6d48ae25e897b1569161bd45131d8cf847c47abed7287c",
    "url": "https://docs.oracle.com/en/java/javase/25/docs/api/java.base/java/util/concurrent/atomic/AtomicLong.html",
    "parameters": [
      {
        "name": "expectedValue",
        "type": "long",
        "has_default": false,
        "default_value": null,
        "is_keyword_only": false,
        "is_var_args": false,
        "is_var_kwargs": false,
        "description": ""
      },
      {
        "name": "newValue",
        "type": "long",
        "has_default": false,
        "default_value": null,
        "is_keyword_only": false,
        "is_var_args": false,
        "is_var_kwargs": false,
        "description": ""
      }
    ],
    "return_type": "final boolean",
    "exceptions": [],
    "description": "Possibly atomically sets the value tonewValueif the current value== expectedValue,\nwith memory effects as specified byVarHandle.weakCompareAndSetRelease(Object...).",
    "example": "",
    "articles": [],
    "info": {
      "status": "empty",
      "excerpt": "Possibly atomically sets the value tonewValueif the current value== expectedValue,\nwith memory effects as specified byVarHandle.weakCompareAndSetRelease(Object...).",
      "keyword": "",
      "seo_position": 0,
      "visits": 0
    },
    "createdDate": "2026-03-11T23:15:40.857610",
    "updatedDate": "2026-03-11T23:15:40.857610",
    "metadata": {
      "deprecated": true,
      "deprecated_version": "unknown",
      "added_version": "1.5",
      "tags": [],
      "difficulty": null,
      "popularity_score": 0
    }
  },
  "java.util.concurrent.atomic/AtomicReference/weakCompareAndSetRelease": {
    "id": "java.util.concurrent.atomic.AtomicReference.weakCompareAndSetRelease",
    "name": "weakCompareAndSetRelease",
    "type": "method",
    "parent": "AtomicReference",
    "signatures": [
      "public final boolean weakCompareAndSetRelease(V expectedValue, V newValue)"
    ],
    "signature_hash": "03c65039507045fbf9e550cad8d042f904e59a262d76c833839945143382bee6",
    "url": "https://docs.oracle.com/en/java/javase/25/docs/api/java.base/java/util/concurrent/atomic/AtomicReference.html",
    "parameters": [
      {
        "name": "expectedValue",
        "type": "V",
        "has_default": false,
        "default_value": null,
        "is_keyword_only": false,
        "is_var_args": false,
        "is_var_kwargs": false,
        "description": ""
      },
      {
        "name": "newValue",
        "type": "V",
        "has_default": false,
        "default_value": null,
        "is_keyword_only": false,
        "is_var_args": false,
        "is_var_kwargs": false,
        "description": ""
      }
    ],
    "return_type": "final boolean",
    "exceptions": [],
    "description": "Possibly atomically sets the value tonewValueif the current value== expectedValue,\nwith memory effects as specified byVarHandle.weakCompareAndSetRelease(Object...).",
    "example": "",
    "articles": [],
    "info": {
      "status": "empty",
      "excerpt": "Possibly atomically sets the value tonewValueif the current value== expectedValue,\nwith memory effects as specified byVarHandle.weakCompareAndSetRelease(Object...).",
      "keyword": "",
      "seo_position": 0,
      "visits": 0
    },
    "createdDate": "2026-03-11T23:15:40.858249",
    "updatedDate": "2026-03-11T23:15:40.858250",
    "metadata": {
      "deprecated": true,
      "deprecated_version": "unknown",
      "added_version": "1.5",
      "tags": [],
      "difficulty": null,
      "popularity_score": 0
    }
  },
  "java.util.concurrent.atomic/AtomicIntegerArray/weakCompareAndSetRelease": {
    "id": "java.util.concurrent.atomic.AtomicIntegerArray.weakCompareAndSetRelease",
    "name": "weakCompareAndSetRelease",
    "type": "method",
    "parent": "AtomicIntegerArray",
    "signatures": [
      "public final boolean weakCompareAndSetRelease(int i, int expectedValue, int newValue)"
    ],
    "signature_hash": "dde5ab8004586a5db5e8b5099cb391ec3b2f205d457dd3fe483eeb50ea6329fc",
    "url": "https://docs.oracle.com/en/java/javase/25/docs/api/java.base/java/util/concurrent/atomic/AtomicIntegerArray.html",
    "parameters": [
      {
        "name": "i",
        "type": "int",
        "has_default": false,
        "default_value": null,
        "is_keyword_only": false,
        "is_var_args": false,
        "is_var_kwargs": false,
        "description": ""
      },
      {
        "name": "expectedValue",
        "type": "int",
        "has_default": false,
        "default_value": null,
        "is_keyword_only": false,
        "is_var_args": false,
        "is_var_kwargs": false,
        "description": ""
      },
      {
        "name": "newValue",
        "type": "int",
        "has_default": false,
        "default_value": null,
        "is_keyword_only": false,
        "is_var_args": false,
        "is_var_kwargs": false,
        "description": ""
      }
    ],
    "return_type": "final boolean",
    "exceptions": [],
    "description": "Possibly atomically sets the element at indexitonewValueif the element's current value== expectedValue,\nwith memory effects as specified byVarHandle.weakCompareAndSetRelease(Object...).",
    "example": "",
    "articles": [],
    "info": {
      "status": "empty",
      "excerpt": "Possibly atomically sets the element at indexitonewValueif the element's current value== expectedValue,\nwith memory effects as specified byVarHandle.weakCompareAndSetRelease(Object...).",
      "keyword": "",
      "seo_position": 0,
      "visits": 0
    },
    "createdDate": "2026-03-11T23:15:40.859193",
    "updatedDate": "2026-03-11T23:15:40.859194",
    "metadata": {
      "deprecated": true,
      "deprecated_version": "unknown",
      "added_version": "1.5",
      "tags": [],
      "difficulty": null,
      "popularity_score": 0
    }
  },
  "java.util.concurrent.atomic/AtomicLongArray/weakCompareAndSetRelease": {
    "id": "java.util.concurrent.atomic.AtomicLongArray.weakCompareAndSetRelease",
    "name": "weakCompareAndSetRelease",
    "type": "method",
    "parent": "AtomicLongArray",
    "signatures": [
      "public final boolean weakCompareAndSetRelease(int i, long expectedValue, long newValue)"
    ],
    "signature_hash": "6bd39491ff22ba8f25146795a0ec94aff97b8963010b1dde72ec1ec8446c36d2",
    "url": "https://docs.oracle.com/en/java/javase/25/docs/api/java.base/java/util/concurrent/atomic/AtomicLongArray.html",
    "parameters": [
      {
        "name": "i",
        "type": "int",
        "has_default": false,
        "default_value": null,
        "is_keyword_only": false,
        "is_var_args": false,
        "is_var_kwargs": false,
        "description": ""
      },
      {
        "name": "expectedValue",
        "type": "long",
        "has_default": false,
        "default_value": null,
        "is_keyword_only": false,
        "is_var_args": false,
        "is_var_kwargs": false,
        "description": ""
      },
      {
        "name": "newValue",
        "type": "long",
        "has_default": false,
        "default_value": null,
        "is_keyword_only": false,
        "is_var_args": false,
        "is_var_kwargs": false,
        "description": ""
      }
    ],
    "return_type": "final boolean",
    "exceptions": [],
    "description": "Possibly atomically sets the element at indexitonewValueif the element's current value== expectedValue,\nwith memory effects as specified byVarHandle.weakCompareAndSetRelease(Object...).",
    "example": "",
    "articles": [],
    "info": {
      "status": "empty",
      "excerpt": "Possibly atomically sets the element at indexitonewValueif the element's current value== expectedValue,\nwith memory effects as specified byVarHandle.weakCompareAndSetRelease(Object...).",
      "keyword": "",
      "seo_position": 0,
      "visits": 0
    },
    "createdDate": "2026-03-11T23:15:40.860173",
    "updatedDate": "2026-03-11T23:15:40.860174",
    "metadata": {
      "deprecated": true,
      "deprecated_version": "unknown",
      "added_version": "1.5",
      "tags": [],
      "difficulty": null,
      "popularity_score": 0
    }
  },
  "java.util.concurrent.atomic/AtomicReferenceArray/weakCompareAndSetRelease": {
    "id": "java.util.concurrent.atomic.AtomicReferenceArray.weakCompareAndSetRelease",
    "name": "weakCompareAndSetRelease",
    "type": "method",
    "parent": "AtomicReferenceArray",
    "signatures": [
      "public final boolean weakCompareAndSetRelease(int i, E expectedValue, E newValue)"
    ],
    "signature_hash": "55ce8bac11c756cf0ed911ce318369ab2c67d7bb7c22e0bc0a73104d6efd4a5b",
    "url": "https://docs.oracle.com/en/java/javase/25/docs/api/java.base/java/util/concurrent/atomic/AtomicReferenceArray.html",
    "parameters": [
      {
        "name": "i",
        "type": "int",
        "has_default": false,
        "default_value": null,
        "is_keyword_only": false,
        "is_var_args": false,
        "is_var_kwargs": false,
        "description": ""
      },
      {
        "name": "expectedValue",
        "type": "E",
        "has_default": false,
        "default_value": null,
        "is_keyword_only": false,
        "is_var_args": false,
        "is_var_kwargs": false,
        "description": ""
      },
      {
        "name": "newValue",
        "type": "E",
        "has_default": false,
        "default_value": null,
        "is_keyword_only": false,
        "is_var_args": false,
        "is_var_kwargs": false,
        "description": ""
      }
    ],
    "return_type": "final boolean",
    "exceptions": [],
    "description": "Possibly atomically sets the element at indexitonewValueif the element's current value== expectedValue,\nwith memory effects as specified byVarHandle.weakCompareAndSetRelease(Object...).",
    "example": "",
    "articles": [],
    "info": {
      "status": "empty",
      "excerpt": "Possibly atomically sets the element at indexitonewValueif the element's current value== expectedValue,\nwith memory effects as specified byVarHandle.weakCompareAndSetRelease(Object...).",
      "keyword": "",
      "seo_position": 0,
      "visits": 0
    },
    "createdDate": "2026-03-11T23:15:40.861054",
    "updatedDate": "2026-03-11T23:15:40.861055",
    "metadata": {
      "deprecated": true,
      "deprecated_version": "unknown",
      "added_version": "1.5",
      "tags": [],
      "difficulty": null,
      "popularity_score": 0
    }
  },
  "java.util.concurrent.atomic/AtomicBoolean/weakCompareAndSetVolatile": {
    "id": "java.util.concurrent.atomic.AtomicBoolean.weakCompareAndSetVolatile",
    "name": "weakCompareAndSetVolatile",
    "type": "method",
    "parent": "AtomicBoolean",
    "signatures": [
      "public final boolean weakCompareAndSetVolatile(boolean expectedValue, boolean newValue)"
    ],
    "signature_hash": "d0d13f82a30b920d4414b29f20736d2c1ca17a5eb08315df35c1586b9058dec9",
    "url": "https://docs.oracle.com/en/java/javase/25/docs/api/java.base/java/util/concurrent/atomic/AtomicBoolean.html",
    "parameters": [
      {
        "name": "expectedValue",
        "type": "boolean",
        "has_default": false,
        "default_value": null,
        "is_keyword_only": false,
        "is_var_args": false,
        "is_var_kwargs": false,
        "description": ""
      },
      {
        "name": "newValue",
        "type": "boolean",
        "has_default": false,
        "default_value": null,
        "is_keyword_only": false,
        "is_var_args": false,
        "is_var_kwargs": false,
        "description": ""
      }
    ],
    "return_type": "final boolean",
    "exceptions": [],
    "description": "Possibly atomically sets the value tonewValueif the current\nvalue== expectedValue,\nwith memory effects as specified byVarHandle.weakCompareAndSet(Object...).",
    "example": "",
    "articles": [],
    "info": {
      "status": "empty",
      "excerpt": "Possibly atomically sets the value tonewValueif the current\nvalue== expectedValue,\nwith memory effects as specified byVarHandle.weakCompareAndSet(Object...).",
      "keyword": "",
      "seo_position": 0,
      "visits": 0
    },
    "createdDate": "2026-03-11T23:15:40.855594",
    "updatedDate": "2026-03-11T23:15:40.855595",
    "metadata": {
      "deprecated": true,
      "deprecated_version": "unknown",
      "added_version": "1.5",
      "tags": [],
      "difficulty": null,
      "popularity_score": 0
    }
  },
  "java.util.concurrent.atomic/AtomicInteger/weakCompareAndSetVolatile": {
    "id": "java.util.concurrent.atomic.AtomicInteger.weakCompareAndSetVolatile",
    "name": "weakCompareAndSetVolatile",
    "type": "method",
    "parent": "AtomicInteger",
    "signatures": [
      "public final boolean weakCompareAndSetVolatile(int expectedValue, int newValue)"
    ],
    "signature_hash": "ef4959576a9d8a6fcd66197993a83645da1bd27940aa172aa5050d40c45d8018",
    "url": "https://docs.oracle.com/en/java/javase/25/docs/api/java.base/java/util/concurrent/atomic/AtomicInteger.html",
    "parameters": [
      {
        "name": "expectedValue",
        "type": "int",
        "has_default": false,
        "default_value": null,
        "is_keyword_only": false,
        "is_var_args": false,
        "is_var_kwargs": false,
        "description": ""
      },
      {
        "name": "newValue",
        "type": "int",
        "has_default": false,
        "default_value": null,
        "is_keyword_only": false,
        "is_var_args": false,
        "is_var_kwargs": false,
        "description": ""
      }
    ],
    "return_type": "final boolean",
    "exceptions": [],
    "description": "Possibly atomically sets the value tonewValueif\nthe current value== expectedValue,\nwith memory effects as specified byVarHandle.weakCompareAndSet(Object...).",
    "example": "",
    "articles": [],
    "info": {
      "status": "empty",
      "excerpt": "Possibly atomically sets the value tonewValueif\nthe current value== expectedValue,\nwith memory effects as specified byVarHandle.weakCompareAndSet(Object...).",
      "keyword": "",
      "seo_position": 0,
      "visits": 0
    },
    "createdDate": "2026-03-11T23:15:40.856722",
    "updatedDate": "2026-03-11T23:15:40.856723",
    "metadata": {
      "deprecated": true,
      "deprecated_version": "unknown",
      "added_version": "1.5",
      "tags": [],
      "difficulty": null,
      "popularity_score": 0
    }
  },
  "java.util.concurrent.atomic/AtomicLong/weakCompareAndSetVolatile": {
    "id": "java.util.concurrent.atomic.AtomicLong.weakCompareAndSetVolatile",
    "name": "weakCompareAndSetVolatile",
    "type": "method",
    "parent": "AtomicLong",
    "signatures": [
      "public final boolean weakCompareAndSetVolatile(long expectedValue, long newValue)"
    ],
    "signature_hash": "b0d532d85d9bb766360a4357587b4f74a42c6d17bb7bef7c3201834764dd1549",
    "url": "https://docs.oracle.com/en/java/javase/25/docs/api/java.base/java/util/concurrent/atomic/AtomicLong.html",
    "parameters": [
      {
        "name": "expectedValue",
        "type": "long",
        "has_default": false,
        "default_value": null,
        "is_keyword_only": false,
        "is_var_args": false,
        "is_var_kwargs": false,
        "description": ""
      },
      {
        "name": "newValue",
        "type": "long",
        "has_default": false,
        "default_value": null,
        "is_keyword_only": false,
        "is_var_args": false,
        "is_var_kwargs": false,
        "description": ""
      }
    ],
    "return_type": "final boolean",
    "exceptions": [],
    "description": "Possibly atomically sets the value tonewValueif the current value== expectedValue,\nwith memory effects as specified byVarHandle.weakCompareAndSet(Object...).",
    "example": "",
    "articles": [],
    "info": {
      "status": "empty",
      "excerpt": "Possibly atomically sets the value tonewValueif the current value== expectedValue,\nwith memory effects as specified byVarHandle.weakCompareAndSet(Object...).",
      "keyword": "",
      "seo_position": 0,
      "visits": 0
    },
    "createdDate": "2026-03-11T23:15:40.857636",
    "updatedDate": "2026-03-11T23:15:40.857637",
    "metadata": {
      "deprecated": true,
      "deprecated_version": "unknown",
      "added_version": "1.5",
      "tags": [],
      "difficulty": null,
      "popularity_score": 0
    }
  },
  "java.util.concurrent.atomic/AtomicReference/weakCompareAndSetVolatile": {
    "id": "java.util.concurrent.atomic.AtomicReference.weakCompareAndSetVolatile",
    "name": "weakCompareAndSetVolatile",
    "type": "method",
    "parent": "AtomicReference",
    "signatures": [
      "public final boolean weakCompareAndSetVolatile(V expectedValue, V newValue)"
    ],
    "signature_hash": "1317cfae78f3f761f32ef77e344d7cbc7cfa8c42f68c0ba51e8a56f43b6247d3",
    "url": "https://docs.oracle.com/en/java/javase/25/docs/api/java.base/java/util/concurrent/atomic/AtomicReference.html",
    "parameters": [
      {
        "name": "expectedValue",
        "type": "V",
        "has_default": false,
        "default_value": null,
        "is_keyword_only": false,
        "is_var_args": false,
        "is_var_kwargs": false,
        "description": ""
      },
      {
        "name": "newValue",
        "type": "V",
        "has_default": false,
        "default_value": null,
        "is_keyword_only": false,
        "is_var_args": false,
        "is_var_kwargs": false,
        "description": ""
      }
    ],
    "return_type": "final boolean",
    "exceptions": [],
    "description": "Possibly atomically sets the value tonewValueif the current value== expectedValue,\nwith memory effects as specified byVarHandle.weakCompareAndSet(Object...).",
    "example": "",
    "articles": [],
    "info": {
      "status": "empty",
      "excerpt": "Possibly atomically sets the value tonewValueif the current value== expectedValue,\nwith memory effects as specified byVarHandle.weakCompareAndSet(Object...).",
      "keyword": "",
      "seo_position": 0,
      "visits": 0
    },
    "createdDate": "2026-03-11T23:15:40.858272",
    "updatedDate": "2026-03-11T23:15:40.858273",
    "metadata": {
      "deprecated": true,
      "deprecated_version": "unknown",
      "added_version": "1.5",
      "tags": [],
      "difficulty": null,
      "popularity_score": 0
    }
  },
  "java.util.concurrent.atomic/AtomicIntegerArray/weakCompareAndSetVolatile": {
    "id": "java.util.concurrent.atomic.AtomicIntegerArray.weakCompareAndSetVolatile",
    "name": "weakCompareAndSetVolatile",
    "type": "method",
    "parent": "AtomicIntegerArray",
    "signatures": [
      "public final boolean weakCompareAndSetVolatile(int i, int expectedValue, int newValue)"
    ],
    "signature_hash": "d74b1e714e1c3d22b467c8a2cd05ff1b6e0dfad76474f181ce33be3fdb36f7a6",
    "url": "https://docs.oracle.com/en/java/javase/25/docs/api/java.base/java/util/concurrent/atomic/AtomicIntegerArray.html",
    "parameters": [
      {
        "name": "i",
        "type": "int",
        "has_default": false,
        "default_value": null,
        "is_keyword_only": false,
        "is_var_args": false,
        "is_var_kwargs": false,
        "description": ""
      },
      {
        "name": "expectedValue",
        "type": "int",
        "has_default": false,
        "default_value": null,
        "is_keyword_only": false,
        "is_var_args": false,
        "is_var_kwargs": false,
        "description": ""
      },
      {
        "name": "newValue",
        "type": "int",
        "has_default": false,
        "default_value": null,
        "is_keyword_only": false,
        "is_var_args": false,
        "is_var_kwargs": false,
        "description": ""
      }
    ],
    "return_type": "final boolean",
    "exceptions": [],
    "description": "Possibly atomically sets the element at indexitonewValueif the element's current value== expectedValue,\nwith memory effects as specified byVarHandle.weakCompareAndSet(Object...).",
    "example": "",
    "articles": [],
    "info": {
      "status": "empty",
      "excerpt": "Possibly atomically sets the element at indexitonewValueif the element's current value== expectedValue,\nwith memory effects as specified byVarHandle.weakCompareAndSet(Object...).",
      "keyword": "",
      "seo_position": 0,
      "visits": 0
    },
    "createdDate": "2026-03-11T23:15:40.859233",
    "updatedDate": "2026-03-11T23:15:40.859237",
    "metadata": {
      "deprecated": true,
      "deprecated_version": "unknown",
      "added_version": "1.5",
      "tags": [],
      "difficulty": null,
      "popularity_score": 0
    }
  },
  "java.util.concurrent.atomic/AtomicLongArray/weakCompareAndSetVolatile": {
    "id": "java.util.concurrent.atomic.AtomicLongArray.weakCompareAndSetVolatile",
    "name": "weakCompareAndSetVolatile",
    "type": "method",
    "parent": "AtomicLongArray",
    "signatures": [
      "public final boolean weakCompareAndSetVolatile(int i, long expectedValue, long newValue)"
    ],
    "signature_hash": "c7440d62596084910e9f10b97d30703d86390174259f8422e201cff284eebae2",
    "url": "https://docs.oracle.com/en/java/javase/25/docs/api/java.base/java/util/concurrent/atomic/AtomicLongArray.html",
    "parameters": [
      {
        "name": "i",
        "type": "int",
        "has_default": false,
        "default_value": null,
        "is_keyword_only": false,
        "is_var_args": false,
        "is_var_kwargs": false,
        "description": ""
      },
      {
        "name": "expectedValue",
        "type": "long",
        "has_default": false,
        "default_value": null,
        "is_keyword_only": false,
        "is_var_args": false,
        "is_var_kwargs": false,
        "description": ""
      },
      {
        "name": "newValue",
        "type": "long",
        "has_default": false,
        "default_value": null,
        "is_keyword_only": false,
        "is_var_args": false,
        "is_var_kwargs": false,
        "description": ""
      }
    ],
    "return_type": "final boolean",
    "exceptions": [],
    "description": "Possibly atomically sets the element at indexitonewValueif the element's current value== expectedValue,\nwith memory effects as specified byVarHandle.weakCompareAndSet(Object...).",
    "example": "",
    "articles": [],
    "info": {
      "status": "empty",
      "excerpt": "Possibly atomically sets the element at indexitonewValueif the element's current value== expectedValue,\nwith memory effects as specified byVarHandle.weakCompareAndSet(Object...).",
      "keyword": "",
      "seo_position": 0,
      "visits": 0
    },
    "createdDate": "2026-03-11T23:15:40.860202",
    "updatedDate": "2026-03-11T23:15:40.860203",
    "metadata": {
      "deprecated": true,
      "deprecated_version": "unknown",
      "added_version": "1.5",
      "tags": [],
      "difficulty": null,
      "popularity_score": 0
    }
  },
  "java.util.concurrent.atomic/AtomicReferenceArray/weakCompareAndSetVolatile": {
    "id": "java.util.concurrent.atomic.AtomicReferenceArray.weakCompareAndSetVolatile",
    "name": "weakCompareAndSetVolatile",
    "type": "method",
    "parent": "AtomicReferenceArray",
    "signatures": [
      "public final boolean weakCompareAndSetVolatile(int i, E expectedValue, E newValue)"
    ],
    "signature_hash": "49bfbc0d5d088f8e9f0e3bf1f8437f4af5d48b5a427f493ba53c634e012f2dee",
    "url": "https://docs.oracle.com/en/java/javase/25/docs/api/java.base/java/util/concurrent/atomic/AtomicReferenceArray.html",
    "parameters": [
      {
        "name": "i",
        "type": "int",
        "has_default": false,
        "default_value": null,
        "is_keyword_only": false,
        "is_var_args": false,
        "is_var_kwargs": false,
        "description": ""
      },
      {
        "name": "expectedValue",
        "type": "E",
        "has_default": false,
        "default_value": null,
        "is_keyword_only": false,
        "is_var_args": false,
        "is_var_kwargs": false,
        "description": ""
      },
      {
        "name": "newValue",
        "type": "E",
        "has_default": false,
        "default_value": null,
        "is_keyword_only": false,
        "is_var_args": false,
        "is_var_kwargs": false,
        "description": ""
      }
    ],
    "return_type": "final boolean",
    "exceptions": [],
    "description": "Possibly atomically sets the element at indexitonewValueif the element's current value== expectedValue,\nwith memory effects as specified byVarHandle.weakCompareAndSet(Object...).",
    "example": "",
    "articles": [],
    "info": {
      "status": "empty",
      "excerpt": "Possibly atomically sets the element at indexitonewValueif the element's current value== expectedValue,\nwith memory effects as specified byVarHandle.weakCompareAndSet(Object...).",
      "keyword": "",
      "seo_position": 0,
      "visits": 0
    },
    "createdDate": "2026-03-11T23:15:40.861082",
    "updatedDate": "2026-03-11T23:15:40.861082",
    "metadata": {
      "deprecated": true,
      "deprecated_version": "unknown",
      "added_version": "1.5",
      "tags": [],
      "difficulty": null,
      "popularity_score": 0
    }
  }
}