{
  "java.util.function/DoubleBinaryOperator": {
    "id": "java.util.function.DoubleBinaryOperator",
    "name": "DoubleBinaryOperator",
    "type": "interface",
    "parent": null,
    "signatures": [],
    "signature_hash": "e3b0c44298fc1c149afbf4c8996fb92427ae41e4649b934ca495991b7852b855",
    "url": "https://docs.oracle.com/en/java/javase/25/docs/api/java.base/java/util/function/DoubleBinaryOperator.html",
    "parameters": [],
    "return_type": "",
    "exceptions": [],
    "description": "",
    "example": "",
    "articles": [],
    "info": {
      "status": "empty",
      "excerpt": "",
      "keyword": "",
      "seo_position": 0,
      "visits": 0
    },
    "createdDate": "2026-03-08T21:40:21.475330",
    "updatedDate": "2026-03-08T21:40:21.475331",
    "metadata": {
      "deprecated": false,
      "deprecated_version": null,
      "added_version": "1.8",
      "tags": [],
      "difficulty": null,
      "popularity_score": 0
    },
    "methods": [
      "applyAsDouble"
    ]
  },
  "java.util.function/DoubleConsumer": {
    "id": "java.util.function.DoubleConsumer",
    "name": "DoubleConsumer",
    "type": "interface",
    "parent": null,
    "signatures": [],
    "signature_hash": "e3b0c44298fc1c149afbf4c8996fb92427ae41e4649b934ca495991b7852b855",
    "url": "https://docs.oracle.com/en/java/javase/25/docs/api/java.base/java/util/function/DoubleConsumer.html",
    "parameters": [],
    "return_type": "",
    "exceptions": [],
    "description": "",
    "example": "",
    "articles": [],
    "info": {
      "status": "empty",
      "excerpt": "",
      "keyword": "",
      "seo_position": 0,
      "visits": 0
    },
    "createdDate": "2026-03-08T21:40:21.475098",
    "updatedDate": "2026-03-08T21:40:21.475098",
    "metadata": {
      "deprecated": false,
      "deprecated_version": null,
      "added_version": "1.8",
      "tags": [],
      "difficulty": null,
      "popularity_score": 0
    },
    "methods": [
      "accept",
      "andThen"
    ]
  },
  "java.util.function/DoubleFunction<R>": {
    "id": "java.util.function.DoubleFunction<R>",
    "name": "DoubleFunction<R>",
    "type": "interface",
    "parent": null,
    "signatures": [],
    "signature_hash": "e3b0c44298fc1c149afbf4c8996fb92427ae41e4649b934ca495991b7852b855",
    "url": "https://docs.oracle.com/en/java/javase/25/docs/api/java.base/java/util/function/DoubleFunction.html",
    "parameters": [],
    "return_type": "",
    "exceptions": [],
    "description": "",
    "example": "",
    "articles": [],
    "info": {
      "status": "empty",
      "excerpt": "",
      "keyword": "",
      "seo_position": 0,
      "visits": 0
    },
    "createdDate": "2026-03-08T21:40:21.475357",
    "updatedDate": "2026-03-08T21:40:21.475358",
    "metadata": {
      "deprecated": false,
      "deprecated_version": null,
      "added_version": "1.8",
      "tags": [],
      "difficulty": null,
      "popularity_score": 0
    },
    "methods": [
      "apply"
    ]
  },
  "java.util.function/DoublePredicate": {
    "id": "java.util.function.DoublePredicate",
    "name": "DoublePredicate",
    "type": "interface",
    "parent": null,
    "signatures": [],
    "signature_hash": "e3b0c44298fc1c149afbf4c8996fb92427ae41e4649b934ca495991b7852b855",
    "url": "https://docs.oracle.com/en/java/javase/25/docs/api/java.base/java/util/function/DoublePredicate.html",
    "parameters": [],
    "return_type": "",
    "exceptions": [],
    "description": "",
    "example": "",
    "articles": [],
    "info": {
      "status": "empty",
      "excerpt": "",
      "keyword": "",
      "seo_position": 0,
      "visits": 0
    },
    "createdDate": "2026-03-08T21:40:21.475389",
    "updatedDate": "2026-03-08T21:40:21.475390",
    "metadata": {
      "deprecated": false,
      "deprecated_version": null,
      "added_version": "1.8",
      "tags": [],
      "difficulty": null,
      "popularity_score": 0
    },
    "methods": [
      "and",
      "negate",
      "or",
      "test"
    ]
  },
  "java.util.function/DoubleSupplier": {
    "id": "java.util.function.DoubleSupplier",
    "name": "DoubleSupplier",
    "type": "interface",
    "parent": null,
    "signatures": [],
    "signature_hash": "e3b0c44298fc1c149afbf4c8996fb92427ae41e4649b934ca495991b7852b855",
    "url": "https://docs.oracle.com/en/java/javase/25/docs/api/java.base/java/util/function/DoubleSupplier.html",
    "parameters": [],
    "return_type": "",
    "exceptions": [],
    "description": "",
    "example": "",
    "articles": [],
    "info": {
      "status": "empty",
      "excerpt": "",
      "keyword": "",
      "seo_position": 0,
      "visits": 0
    },
    "createdDate": "2026-03-08T21:40:21.475463",
    "updatedDate": "2026-03-08T21:40:21.475464",
    "metadata": {
      "deprecated": false,
      "deprecated_version": null,
      "added_version": "1.8",
      "tags": [],
      "difficulty": null,
      "popularity_score": 0
    },
    "methods": [
      "getAsDouble"
    ]
  },
  "java.util.function/DoubleToIntFunction": {
    "id": "java.util.function.DoubleToIntFunction",
    "name": "DoubleToIntFunction",
    "type": "interface",
    "parent": null,
    "signatures": [],
    "signature_hash": "e3b0c44298fc1c149afbf4c8996fb92427ae41e4649b934ca495991b7852b855",
    "url": "https://docs.oracle.com/en/java/javase/25/docs/api/java.base/java/util/function/DoubleToIntFunction.html",
    "parameters": [],
    "return_type": "",
    "exceptions": [],
    "description": "",
    "example": "",
    "articles": [],
    "info": {
      "status": "empty",
      "excerpt": "",
      "keyword": "",
      "seo_position": 0,
      "visits": 0
    },
    "createdDate": "2026-03-08T21:40:21.475486",
    "updatedDate": "2026-03-08T21:40:21.475487",
    "metadata": {
      "deprecated": false,
      "deprecated_version": null,
      "added_version": "1.8",
      "tags": [],
      "difficulty": null,
      "popularity_score": 0
    },
    "methods": [
      "applyAsInt"
    ]
  },
  "java.util.function/DoubleToLongFunction": {
    "id": "java.util.function.DoubleToLongFunction",
    "name": "DoubleToLongFunction",
    "type": "interface",
    "parent": null,
    "signatures": [],
    "signature_hash": "e3b0c44298fc1c149afbf4c8996fb92427ae41e4649b934ca495991b7852b855",
    "url": "https://docs.oracle.com/en/java/javase/25/docs/api/java.base/java/util/function/DoubleToLongFunction.html",
    "parameters": [],
    "return_type": "",
    "exceptions": [],
    "description": "",
    "example": "",
    "articles": [],
    "info": {
      "status": "empty",
      "excerpt": "",
      "keyword": "",
      "seo_position": 0,
      "visits": 0
    },
    "createdDate": "2026-03-08T21:40:21.475511",
    "updatedDate": "2026-03-08T21:40:21.475512",
    "metadata": {
      "deprecated": false,
      "deprecated_version": null,
      "added_version": "1.8",
      "tags": [],
      "difficulty": null,
      "popularity_score": 0
    },
    "methods": [
      "applyAsLong"
    ]
  },
  "java.util.function/DoubleUnaryOperator": {
    "id": "java.util.function.DoubleUnaryOperator",
    "name": "DoubleUnaryOperator",
    "type": "interface",
    "parent": null,
    "signatures": [],
    "signature_hash": "e3b0c44298fc1c149afbf4c8996fb92427ae41e4649b934ca495991b7852b855",
    "url": "https://docs.oracle.com/en/java/javase/25/docs/api/java.base/java/util/function/DoubleUnaryOperator.html",
    "parameters": [],
    "return_type": "",
    "exceptions": [],
    "description": "",
    "example": "",
    "articles": [],
    "info": {
      "status": "empty",
      "excerpt": "",
      "keyword": "",
      "seo_position": 0,
      "visits": 0
    },
    "createdDate": "2026-03-08T21:40:21.475538",
    "updatedDate": "2026-03-08T21:40:21.475539",
    "metadata": {
      "deprecated": false,
      "deprecated_version": null,
      "added_version": "1.8",
      "tags": [],
      "difficulty": null,
      "popularity_score": 0
    },
    "methods": [
      "andThen",
      "applyAsDouble",
      "compose",
      "identity"
    ]
  }
}