{
  "pyclbr/Function/lineno": {
    "id": "pyclbr.Function.lineno",
    "name": "lineno",
    "type": "attribute",
    "parent": "Function",
    "signatures": [
      "lineno"
    ],
    "signature_hash": "ad4af9cdd17f438a7a58953562c3c804a95da56c812af0705ee779ba079133d1",
    "url": "https://docs.python.org/3/library/pyclbr.html#module-pyclbr#pyclbr.Function.lineno",
    "parameters": [],
    "return_type": "",
    "exceptions": [],
    "description": {
      "es": "",
      "en": "The line number in the file where the definition starts."
    },
    "example": "",
    "articles": [],
    "info": {
      "status": "empty",
      "excerpt": {
        "es": "The line number in the file where the definition starts.",
        "en": "The line number in the file where the definition starts."
      },
      "keyword": "",
      "seo_position": 0,
      "visits": 0
    },
    "createdDate": "2026-04-03T00:22:09.299296",
    "updatedDate": "2026-04-03T00:22:09.299297",
    "metadata": {
      "status": "current",
      "deprecated_version": null,
      "added_version": null,
      "tags": [],
      "difficulty": null,
      "popularity_score": 0
    }
  },
  "pyclbr/Class/lineno": {
    "id": "pyclbr.Class.lineno",
    "name": "lineno",
    "type": "attribute",
    "parent": "Class",
    "signatures": [
      "lineno"
    ],
    "signature_hash": "ad4af9cdd17f438a7a58953562c3c804a95da56c812af0705ee779ba079133d1",
    "url": "https://docs.python.org/3/library/pyclbr.html#module-pyclbr#pyclbr.Class.lineno",
    "parameters": [],
    "return_type": "",
    "exceptions": [],
    "description": {
      "es": "",
      "en": "The line number in the file where the definition starts."
    },
    "example": "",
    "articles": [],
    "info": {
      "status": "empty",
      "excerpt": {
        "es": "The line number in the file where the definition starts.",
        "en": "The line number in the file where the definition starts."
      },
      "keyword": "",
      "seo_position": 0,
      "visits": 0
    },
    "createdDate": "2026-04-03T00:22:09.299407",
    "updatedDate": "2026-04-03T00:22:09.299408",
    "metadata": {
      "status": "current",
      "deprecated_version": null,
      "added_version": null,
      "tags": [],
      "difficulty": null,
      "popularity_score": 0
    }
  }
}